[
  {
    "<TICKER>": "US1.AMZN",
    "<PER>": "D",
    "<DATE>": "01/02/19",
    "<TIME>": "00:00:00",
    "<CLOSE>": 1539.56
  },
  {
    "<TICKER>": "US1.AMZN",
    "<PER>": "D",
    "<DATE>": "01/03/19",
    "<TIME>": "00:00:00",
    "<CLOSE>": 1499.23
  },
  {
    "<TICKER>": "US1.AMZN",
    "<PER>": "D",
    "<DATE>": "01/04/19",
    "<TIME>": "00:00:00",
    "<CLOSE>": 1575.85
  },
  {
    "<TICKER>": "US1.AMZN",
    "<PER>": "D",
    "<DATE>": "01/07/19",
    "<TIME>": "00:00:00",
    "<CLOSE>": 1629.33
  },
  {
    "<TICKER>": "US1.AMZN",
    "<PER>": "D",
    "<DATE>": "01/08/19",
    "<TIME>": "00:00:00",
    "<CLOSE>": 1656.56
  },
  {
    "<TICKER>": "US1.AMZN",
    "<PER>": "D",
    "<DATE>": "01/09/19",
    "<TIME>": "00:00:00",
    "<CLOSE>": 1659.93
  },
  {
    "<TICKER>": "US1.AMZN",
    "<PER>": "D",
    "<DATE>": "01/10/19",
    "<TIME>": "00:00:00",
    "<CLOSE>": 1655.96
  },
  {
    "<TICKER>": "US1.AMZN",
    "<PER>": "D",
    "<DATE>": "01/11/19",
    "<TIME>": "00:00:00",
    "<CLOSE>": 1640.5
  },
  {
    "<TICKER>": "US1.AMZN",
    "<PER>": "D",
    "<DATE>": "01/14/19",
    "<TIME>": "00:00:00",
    "<CLOSE>": 1619.1
  },
  {
    "<TICKER>": "US1.AMZN",
    "<PER>": "D",
    "<DATE>": "01/15/19",
    "<TIME>": "00:00:00",
    "<CLOSE>": 1674.89
  },
  {
    "<TICKER>": "US1.AMZN",
    "<PER>": "D",
    "<DATE>": "01/16/19",
    "<TIME>": "00:00:00",
    "<CLOSE>": 1683.58
  },
  {
    "<TICKER>": "US1.AMZN",
    "<PER>": "D",
    "<DATE>": "01/17/19",
    "<TIME>": "00:00:00",
    "<CLOSE>": 1693.25
  },
  {
    "<TICKER>": "US1.AMZN",
    "<PER>": "D",
    "<DATE>": "01/18/19",
    "<TIME>": "00:00:00",
    "<CLOSE>": 1696.2
  },
  {
    "<TICKER>": "US1.AMZN",
    "<PER>": "D",
    "<DATE>": "01/22/19",
    "<TIME>": "00:00:00",
    "<CLOSE>": 1633.98
  },
  {
    "<TICKER>": "US1.AMZN",
    "<PER>": "D",
    "<DATE>": "01/23/19",
    "<TIME>": "00:00:00",
    "<CLOSE>": 1641.62
  },
  {
    "<TICKER>": "US1.AMZN",
    "<PER>": "D",
    "<DATE>": "01/24/19",
    "<TIME>": "00:00:00",
    "<CLOSE>": 1654.91
  },
  {
    "<TICKER>": "US1.AMZN",
    "<PER>": "D",
    "<DATE>": "01/25/19",
    "<TIME>": "00:00:00",
    "<CLOSE>": 1672.05
  },
  {
    "<TICKER>": "US1.AMZN",
    "<PER>": "D",
    "<DATE>": "01/28/19",
    "<TIME>": "00:00:00",
    "<CLOSE>": 1638.27
  },
  {
    "<TICKER>": "US1.AMZN",
    "<PER>": "D",
    "<DATE>": "01/29/19",
    "<TIME>": "00:00:00",
    "<CLOSE>": 1593.83
  },
  {
    "<TICKER>": "US1.AMZN",
    "<PER>": "D",
    "<DATE>": "01/30/19",
    "<TIME>": "00:00:00",
    "<CLOSE>": 1671.1
  },
  {
    "<TICKER>": "US1.AMZN",
    "<PER>": "D",
    "<DATE>": "01/31/19",
    "<TIME>": "00:00:00",
    "<CLOSE>": 1718.78
  },
  {
    "<TICKER>": "US1.AMZN",
    "<PER>": "D",
    "<DATE>": "02/01/19",
    "<TIME>": "00:00:00",
    "<CLOSE>": 1626.23
  },
  {
    "<TICKER>": "US1.AMZN",
    "<PER>": "D",
    "<DATE>": "02/04/19",
    "<TIME>": "00:00:00",
    "<CLOSE>": 1634.25
  },
  {
    "<TICKER>": "US1.AMZN",
    "<PER>": "D",
    "<DATE>": "02/05/19",
    "<TIME>": "00:00:00",
    "<CLOSE>": 1659.15
  },
  {
    "<TICKER>": "US1.AMZN",
    "<PER>": "D",
    "<DATE>": "02/06/19",
    "<TIME>": "00:00:00",
    "<CLOSE>": 1640.89
  },
  {
    "<TICKER>": "US1.AMZN",
    "<PER>": "D",
    "<DATE>": "02/07/19",
    "<TIME>": "00:00:00",
    "<CLOSE>": 1614.37
  },
  {
    "<TICKER>": "US1.AMZN",
    "<PER>": "D",
    "<DATE>": "02/08/19",
    "<TIME>": "00:00:00",
    "<CLOSE>": 1588.2
  },
  {
    "<TICKER>": "US1.AMZN",
    "<PER>": "D",
    "<DATE>": "02/11/19",
    "<TIME>": "00:00:00",
    "<CLOSE>": 1591.53
  },
  {
    "<TICKER>": "US1.AMZN",
    "<PER>": "D",
    "<DATE>": "02/12/19",
    "<TIME>": "00:00:00",
    "<CLOSE>": 1638.01
  },
  {
    "<TICKER>": "US1.AMZN",
    "<PER>": "D",
    "<DATE>": "02/13/19",
    "<TIME>": "00:00:00",
    "<CLOSE>": 1639.94
  },
  {
    "<TICKER>": "US1.AMZN",
    "<PER>": "D",
    "<DATE>": "02/14/19",
    "<TIME>": "00:00:00",
    "<CLOSE>": 1622.33
  },
  {
    "<TICKER>": "US1.AMZN",
    "<PER>": "D",
    "<DATE>": "02/15/19",
    "<TIME>": "00:00:00",
    "<CLOSE>": 1609.18
  },
  {
    "<TICKER>": "US1.AMZN",
    "<PER>": "D",
    "<DATE>": "02/19/19",
    "<TIME>": "00:00:00",
    "<CLOSE>": 1627.55
  },
  {
    "<TICKER>": "US1.AMZN",
    "<PER>": "D",
    "<DATE>": "02/20/19",
    "<TIME>": "00:00:00",
    "<CLOSE>": 1622.62
  },
  {
    "<TICKER>": "US1.AMZN",
    "<PER>": "D",
    "<DATE>": "02/21/19",
    "<TIME>": "00:00:00",
    "<CLOSE>": 1619.9
  },
  {
    "<TICKER>": "US1.AMZN",
    "<PER>": "D",
    "<DATE>": "02/22/19",
    "<TIME>": "00:00:00",
    "<CLOSE>": 1631.19
  },
  {
    "<TICKER>": "US1.AMZN",
    "<PER>": "D",
    "<DATE>": "02/25/19",
    "<TIME>": "00:00:00",
    "<CLOSE>": 1633
  },
  {
    "<TICKER>": "US1.AMZN",
    "<PER>": "D",
    "<DATE>": "02/26/19",
    "<TIME>": "00:00:00",
    "<CLOSE>": 1636.33
  },
  {
    "<TICKER>": "US1.AMZN",
    "<PER>": "D",
    "<DATE>": "02/27/19",
    "<TIME>": "00:00:00",
    "<CLOSE>": 1641.09
  },
  {
    "<TICKER>": "US1.AMZN",
    "<PER>": "D",
    "<DATE>": "02/28/19",
    "<TIME>": "00:00:00",
    "<CLOSE>": 1639.79
  },
  {
    "<TICKER>": "US1.AMZN",
    "<PER>": "D",
    "<DATE>": "03/01/19",
    "<TIME>": "00:00:00",
    "<CLOSE>": 1671.26
  },
  {
    "<TICKER>": "US1.AMZN",
    "<PER>": "D",
    "<DATE>": "03/04/19",
    "<TIME>": "00:00:00",
    "<CLOSE>": 1696.16
  },
  {
    "<TICKER>": "US1.AMZN",
    "<PER>": "D",
    "<DATE>": "03/05/19",
    "<TIME>": "00:00:00",
    "<CLOSE>": 1691.81
  },
  {
    "<TICKER>": "US1.AMZN",
    "<PER>": "D",
    "<DATE>": "03/06/19",
    "<TIME>": "00:00:00",
    "<CLOSE>": 1669.16
  },
  {
    "<TICKER>": "US1.AMZN",
    "<PER>": "D",
    "<DATE>": "03/07/19",
    "<TIME>": "00:00:00",
    "<CLOSE>": 1626.28
  },
  {
    "<TICKER>": "US1.AMZN",
    "<PER>": "D",
    "<DATE>": "03/08/19",
    "<TIME>": "00:00:00",
    "<CLOSE>": 1622.11
  },
  {
    "<TICKER>": "US1.AMZN",
    "<PER>": "D",
    "<DATE>": "03/11/19",
    "<TIME>": "00:00:00",
    "<CLOSE>": 1670.32
  },
  {
    "<TICKER>": "US1.AMZN",
    "<PER>": "D",
    "<DATE>": "03/12/19",
    "<TIME>": "00:00:00",
    "<CLOSE>": 1672.42
  },
  {
    "<TICKER>": "US1.AMZN",
    "<PER>": "D",
    "<DATE>": "03/13/19",
    "<TIME>": "00:00:00",
    "<CLOSE>": 1690.8
  },
  {
    "<TICKER>": "US1.AMZN",
    "<PER>": "D",
    "<DATE>": "03/14/19",
    "<TIME>": "00:00:00",
    "<CLOSE>": 1685.29
  },
  {
    "<TICKER>": "US1.AMZN",
    "<PER>": "D",
    "<DATE>": "03/15/19",
    "<TIME>": "00:00:00",
    "<CLOSE>": 1712.91
  },
  {
    "<TICKER>": "US1.AMZN",
    "<PER>": "D",
    "<DATE>": "03/18/19",
    "<TIME>": "00:00:00",
    "<CLOSE>": 1742
  },
  {
    "<TICKER>": "US1.AMZN",
    "<PER>": "D",
    "<DATE>": "03/19/19",
    "<TIME>": "00:00:00",
    "<CLOSE>": 1762.7
  },
  {
    "<TICKER>": "US1.AMZN",
    "<PER>": "D",
    "<DATE>": "03/20/19",
    "<TIME>": "00:00:00",
    "<CLOSE>": 1797.73
  },
  {
    "<TICKER>": "US1.AMZN",
    "<PER>": "D",
    "<DATE>": "03/21/19",
    "<TIME>": "00:00:00",
    "<CLOSE>": 1818.4
  },
  {
    "<TICKER>": "US1.AMZN",
    "<PER>": "D",
    "<DATE>": "03/22/19",
    "<TIME>": "00:00:00",
    "<CLOSE>": 1764.06
  },
  {
    "<TICKER>": "US1.AMZN",
    "<PER>": "D",
    "<DATE>": "03/25/19",
    "<TIME>": "00:00:00",
    "<CLOSE>": 1774.07
  },
  {
    "<TICKER>": "US1.AMZN",
    "<PER>": "D",
    "<DATE>": "03/26/19",
    "<TIME>": "00:00:00",
    "<CLOSE>": 1784.47
  },
  {
    "<TICKER>": "US1.AMZN",
    "<PER>": "D",
    "<DATE>": "03/27/19",
    "<TIME>": "00:00:00",
    "<CLOSE>": 1766
  },
  {
    "<TICKER>": "US1.AMZN",
    "<PER>": "D",
    "<DATE>": "03/28/19",
    "<TIME>": "00:00:00",
    "<CLOSE>": 1773.67
  },
  {
    "<TICKER>": "US1.AMZN",
    "<PER>": "D",
    "<DATE>": "03/29/19",
    "<TIME>": "00:00:00",
    "<CLOSE>": 1781.09
  },
  {
    "<TICKER>": "US1.AMZN",
    "<PER>": "D",
    "<DATE>": "04/01/19",
    "<TIME>": "00:00:00",
    "<CLOSE>": 1814.36
  },
  {
    "<TICKER>": "US1.AMZN",
    "<PER>": "D",
    "<DATE>": "04/02/19",
    "<TIME>": "00:00:00",
    "<CLOSE>": 1814
  },
  {
    "<TICKER>": "US1.AMZN",
    "<PER>": "D",
    "<DATE>": "04/03/19",
    "<TIME>": "00:00:00",
    "<CLOSE>": 1820.41
  },
  {
    "<TICKER>": "US1.AMZN",
    "<PER>": "D",
    "<DATE>": "04/04/19",
    "<TIME>": "00:00:00",
    "<CLOSE>": 1819.51
  },
  {
    "<TICKER>": "US1.AMZN",
    "<PER>": "D",
    "<DATE>": "04/05/19",
    "<TIME>": "00:00:00",
    "<CLOSE>": 1837.65
  },
  {
    "<TICKER>": "US1.AMZN",
    "<PER>": "D",
    "<DATE>": "04/08/19",
    "<TIME>": "00:00:00",
    "<CLOSE>": 1849.679
  },
  {
    "<TICKER>": "US1.AMZN",
    "<PER>": "D",
    "<DATE>": "04/09/19",
    "<TIME>": "00:00:00",
    "<CLOSE>": 1836.52
  },
  {
    "<TICKER>": "US1.AMZN",
    "<PER>": "D",
    "<DATE>": "04/10/19",
    "<TIME>": "00:00:00",
    "<CLOSE>": 1847.33
  },
  {
    "<TICKER>": "US1.AMZN",
    "<PER>": "D",
    "<DATE>": "04/11/19",
    "<TIME>": "00:00:00",
    "<CLOSE>": 1844.5
  },
  {
    "<TICKER>": "US1.AMZN",
    "<PER>": "D",
    "<DATE>": "04/12/19",
    "<TIME>": "00:00:00",
    "<CLOSE>": 1842.96
  },
  {
    "<TICKER>": "US1.AMZN",
    "<PER>": "D",
    "<DATE>": "04/15/19",
    "<TIME>": "00:00:00",
    "<CLOSE>": 1844.85
  },
  {
    "<TICKER>": "US1.AMZN",
    "<PER>": "D",
    "<DATE>": "04/16/19",
    "<TIME>": "00:00:00",
    "<CLOSE>": 1862.92
  },
  {
    "<TICKER>": "US1.AMZN",
    "<PER>": "D",
    "<DATE>": "04/17/19",
    "<TIME>": "00:00:00",
    "<CLOSE>": 1864.82
  },
  {
    "<TICKER>": "US1.AMZN",
    "<PER>": "D",
    "<DATE>": "04/18/19",
    "<TIME>": "00:00:00",
    "<CLOSE>": 1861.4
  },
  {
    "<TICKER>": "US1.AMZN",
    "<PER>": "D",
    "<DATE>": "04/22/19",
    "<TIME>": "00:00:00",
    "<CLOSE>": 1888.04
  },
  {
    "<TICKER>": "US1.AMZN",
    "<PER>": "D",
    "<DATE>": "04/23/19",
    "<TIME>": "00:00:00",
    "<CLOSE>": 1924.17
  },
  {
    "<TICKER>": "US1.AMZN",
    "<PER>": "D",
    "<DATE>": "04/24/19",
    "<TIME>": "00:00:00",
    "<CLOSE>": 1900.88
  },
  {
    "<TICKER>": "US1.AMZN",
    "<PER>": "D",
    "<DATE>": "04/25/19",
    "<TIME>": "00:00:00",
    "<CLOSE>": 1902.16
  },
  {
    "<TICKER>": "US1.AMZN",
    "<PER>": "D",
    "<DATE>": "04/26/19",
    "<TIME>": "00:00:00",
    "<CLOSE>": 1950.9
  },
  {
    "<TICKER>": "US1.AMZN",
    "<PER>": "D",
    "<DATE>": "04/29/19",
    "<TIME>": "00:00:00",
    "<CLOSE>": 1939
  },
  {
    "<TICKER>": "US1.AMZN",
    "<PER>": "D",
    "<DATE>": "04/30/19",
    "<TIME>": "00:00:00",
    "<CLOSE>": 1926.53
  },
  {
    "<TICKER>": "US1.AMZN",
    "<PER>": "D",
    "<DATE>": "05/01/19",
    "<TIME>": "00:00:00",
    "<CLOSE>": 1911.29
  },
  {
    "<TICKER>": "US1.AMZN",
    "<PER>": "D",
    "<DATE>": "05/02/19",
    "<TIME>": "00:00:00",
    "<CLOSE>": 1901.72
  },
  {
    "<TICKER>": "US1.AMZN",
    "<PER>": "D",
    "<DATE>": "05/03/19",
    "<TIME>": "00:00:00",
    "<CLOSE>": 1961.76
  },
  {
    "<TICKER>": "US1.AMZN",
    "<PER>": "D",
    "<DATE>": "05/06/19",
    "<TIME>": "00:00:00",
    "<CLOSE>": 1950.29
  },
  {
    "<TICKER>": "US1.AMZN",
    "<PER>": "D",
    "<DATE>": "05/07/19",
    "<TIME>": "00:00:00",
    "<CLOSE>": 1922.58
  },
  {
    "<TICKER>": "US1.AMZN",
    "<PER>": "D",
    "<DATE>": "05/08/19",
    "<TIME>": "00:00:00",
    "<CLOSE>": 1916.85
  },
  {
    "<TICKER>": "US1.AMZN",
    "<PER>": "D",
    "<DATE>": "05/09/19",
    "<TIME>": "00:00:00",
    "<CLOSE>": 1900.01
  },
  {
    "<TICKER>": "US1.AMZN",
    "<PER>": "D",
    "<DATE>": "05/10/19",
    "<TIME>": "00:00:00",
    "<CLOSE>": 1889.98
  },
  {
    "<TICKER>": "US1.AMZN",
    "<PER>": "D",
    "<DATE>": "05/13/19",
    "<TIME>": "00:00:00",
    "<CLOSE>": 1822.62
  },
  {
    "<TICKER>": "US1.AMZN",
    "<PER>": "D",
    "<DATE>": "05/14/19",
    "<TIME>": "00:00:00",
    "<CLOSE>": 1840.05
  },
  {
    "<TICKER>": "US1.AMZN",
    "<PER>": "D",
    "<DATE>": "05/15/19",
    "<TIME>": "00:00:00",
    "<CLOSE>": 1871.12
  },
  {
    "<TICKER>": "US1.AMZN",
    "<PER>": "D",
    "<DATE>": "05/16/19",
    "<TIME>": "00:00:00",
    "<CLOSE>": 1907.86
  },
  {
    "<TICKER>": "US1.AMZN",
    "<PER>": "D",
    "<DATE>": "05/17/19",
    "<TIME>": "00:00:00",
    "<CLOSE>": 1867.99
  },
  {
    "<TICKER>": "US1.AMZN",
    "<PER>": "D",
    "<DATE>": "05/20/19",
    "<TIME>": "00:00:00",
    "<CLOSE>": 1858.04
  },
  {
    "<TICKER>": "US1.AMZN",
    "<PER>": "D",
    "<DATE>": "05/21/19",
    "<TIME>": "00:00:00",
    "<CLOSE>": 1858.11
  },
  {
    "<TICKER>": "US1.AMZN",
    "<PER>": "D",
    "<DATE>": "05/22/19",
    "<TIME>": "00:00:00",
    "<CLOSE>": 1859.425
  },
  {
    "<TICKER>": "US1.AMZN",
    "<PER>": "D",
    "<DATE>": "05/23/19",
    "<TIME>": "00:00:00",
    "<CLOSE>": 1815.67
  },
  {
    "<TICKER>": "US1.AMZN",
    "<PER>": "D",
    "<DATE>": "05/24/19",
    "<TIME>": "00:00:00",
    "<CLOSE>": 1823.3
  },
  {
    "<TICKER>": "US1.AMZN",
    "<PER>": "D",
    "<DATE>": "05/28/19",
    "<TIME>": "00:00:00",
    "<CLOSE>": 1836.56
  },
  {
    "<TICKER>": "US1.AMZN",
    "<PER>": "D",
    "<DATE>": "05/29/19",
    "<TIME>": "00:00:00",
    "<CLOSE>": 1820.2
  },
  {
    "<TICKER>": "US1.AMZN",
    "<PER>": "D",
    "<DATE>": "05/30/19",
    "<TIME>": "00:00:00",
    "<CLOSE>": 1815.81
  },
  {
    "<TICKER>": "US1.AMZN",
    "<PER>": "D",
    "<DATE>": "05/31/19",
    "<TIME>": "00:00:00",
    "<CLOSE>": 1775.07
  },
  {
    "<TICKER>": "US1.AMZN",
    "<PER>": "D",
    "<DATE>": "06/03/19",
    "<TIME>": "00:00:00",
    "<CLOSE>": 1692.76
  },
  {
    "<TICKER>": "US1.AMZN",
    "<PER>": "D",
    "<DATE>": "06/04/19",
    "<TIME>": "00:00:00",
    "<CLOSE>": 1730.18
  },
  {
    "<TICKER>": "US1.AMZN",
    "<PER>": "D",
    "<DATE>": "06/05/19",
    "<TIME>": "00:00:00",
    "<CLOSE>": 1739.48
  },
  {
    "<TICKER>": "US1.AMZN",
    "<PER>": "D",
    "<DATE>": "06/06/19",
    "<TIME>": "00:00:00",
    "<CLOSE>": 1754.6292
  },
  {
    "<TICKER>": "US1.AMZN",
    "<PER>": "D",
    "<DATE>": "06/07/19",
    "<TIME>": "00:00:00",
    "<CLOSE>": 1804.02
  },
  {
    "<TICKER>": "US1.AMZN",
    "<PER>": "D",
    "<DATE>": "06/10/19",
    "<TIME>": "00:00:00",
    "<CLOSE>": 1860.63
  },
  {
    "<TICKER>": "US1.AMZN",
    "<PER>": "D",
    "<DATE>": "06/11/19",
    "<TIME>": "00:00:00",
    "<CLOSE>": 1863.7
  },
  {
    "<TICKER>": "US1.AMZN",
    "<PER>": "D",
    "<DATE>": "06/12/19",
    "<TIME>": "00:00:00",
    "<CLOSE>": 1855.3
  },
  {
    "<TICKER>": "US1.AMZN",
    "<PER>": "D",
    "<DATE>": "06/13/19",
    "<TIME>": "00:00:00",
    "<CLOSE>": 1870.748
  },
  {
    "<TICKER>": "US1.AMZN",
    "<PER>": "D",
    "<DATE>": "06/14/19",
    "<TIME>": "00:00:00",
    "<CLOSE>": 1870.17
  },
  {
    "<TICKER>": "US1.AMZN",
    "<PER>": "D",
    "<DATE>": "06/17/19",
    "<TIME>": "00:00:00",
    "<CLOSE>": 1886
  },
  {
    "<TICKER>": "US1.AMZN",
    "<PER>": "D",
    "<DATE>": "06/18/19",
    "<TIME>": "00:00:00",
    "<CLOSE>": 1902.15
  },
  {
    "<TICKER>": "US1.AMZN",
    "<PER>": "D",
    "<DATE>": "06/19/19",
    "<TIME>": "00:00:00",
    "<CLOSE>": 1909.03
  },
  {
    "<TICKER>": "US1.AMZN",
    "<PER>": "D",
    "<DATE>": "06/20/19",
    "<TIME>": "00:00:00",
    "<CLOSE>": 1917.95
  },
  {
    "<TICKER>": "US1.AMZN",
    "<PER>": "D",
    "<DATE>": "06/21/19",
    "<TIME>": "00:00:00",
    "<CLOSE>": 1911.1
  },
  {
    "<TICKER>": "US1.AMZN",
    "<PER>": "D",
    "<DATE>": "06/24/19",
    "<TIME>": "00:00:00",
    "<CLOSE>": 1913.96
  },
  {
    "<TICKER>": "US1.AMZN",
    "<PER>": "D",
    "<DATE>": "06/25/19",
    "<TIME>": "00:00:00",
    "<CLOSE>": 1878.64
  },
  {
    "<TICKER>": "US1.AMZN",
    "<PER>": "D",
    "<DATE>": "06/26/19",
    "<TIME>": "00:00:00",
    "<CLOSE>": 1897.75
  },
  {
    "<TICKER>": "US1.AMZN",
    "<PER>": "D",
    "<DATE>": "06/27/19",
    "<TIME>": "00:00:00",
    "<CLOSE>": 1903.67
  },
  {
    "<TICKER>": "US1.AMZN",
    "<PER>": "D",
    "<DATE>": "06/28/19",
    "<TIME>": "00:00:00",
    "<CLOSE>": 1889.83
  },
  {
    "<TICKER>": "US1.AMZN",
    "<PER>": "D",
    "<DATE>": "07/01/19",
    "<TIME>": "00:00:00",
    "<CLOSE>": 1922.26
  },
  {
    "<TICKER>": "US1.AMZN",
    "<PER>": "D",
    "<DATE>": "07/02/19",
    "<TIME>": "00:00:00",
    "<CLOSE>": 1934.79
  },
  {
    "<TICKER>": "US1.AMZN",
    "<PER>": "D",
    "<DATE>": "07/03/19",
    "<TIME>": "00:00:00",
    "<CLOSE>": 1938.25
  },
  {
    "<TICKER>": "US1.AMZN",
    "<PER>": "D",
    "<DATE>": "07/05/19",
    "<TIME>": "00:00:00",
    "<CLOSE>": 1943.1
  },
  {
    "<TICKER>": "US1.AMZN",
    "<PER>": "D",
    "<DATE>": "07/08/19",
    "<TIME>": "00:00:00",
    "<CLOSE>": 1952.33
  },
  {
    "<TICKER>": "US1.AMZN",
    "<PER>": "D",
    "<DATE>": "07/09/19",
    "<TIME>": "00:00:00",
    "<CLOSE>": 1987.35
  },
  {
    "<TICKER>": "US1.AMZN",
    "<PER>": "D",
    "<DATE>": "07/10/19",
    "<TIME>": "00:00:00",
    "<CLOSE>": 2017.77
  },
  {
    "<TICKER>": "US1.AMZN",
    "<PER>": "D",
    "<DATE>": "07/11/19",
    "<TIME>": "00:00:00",
    "<CLOSE>": 2001.07
  },
  {
    "<TICKER>": "US1.AMZN",
    "<PER>": "D",
    "<DATE>": "07/12/19",
    "<TIME>": "00:00:00",
    "<CLOSE>": 2010.02
  },
  {
    "<TICKER>": "US1.AMZN",
    "<PER>": "D",
    "<DATE>": "07/15/19",
    "<TIME>": "00:00:00",
    "<CLOSE>": 2021
  },
  {
    "<TICKER>": "US1.AMZN",
    "<PER>": "D",
    "<DATE>": "07/16/19",
    "<TIME>": "00:00:00",
    "<CLOSE>": 2010
  },
  {
    "<TICKER>": "US1.AMZN",
    "<PER>": "D",
    "<DATE>": "07/17/19",
    "<TIME>": "00:00:00",
    "<CLOSE>": 1992.16
  },
  {
    "<TICKER>": "US1.AMZN",
    "<PER>": "D",
    "<DATE>": "07/18/19",
    "<TIME>": "00:00:00",
    "<CLOSE>": 1978.67
  },
  {
    "<TICKER>": "US1.AMZN",
    "<PER>": "D",
    "<DATE>": "07/19/19",
    "<TIME>": "00:00:00",
    "<CLOSE>": 1965
  },
  {
    "<TICKER>": "US1.AMZN",
    "<PER>": "D",
    "<DATE>": "07/22/19",
    "<TIME>": "00:00:00",
    "<CLOSE>": 1985.92
  },
  {
    "<TICKER>": "US1.AMZN",
    "<PER>": "D",
    "<DATE>": "07/23/19",
    "<TIME>": "00:00:00",
    "<CLOSE>": 1994.47
  },
  {
    "<TICKER>": "US1.AMZN",
    "<PER>": "D",
    "<DATE>": "07/24/19",
    "<TIME>": "00:00:00",
    "<CLOSE>": 2001.04
  },
  {
    "<TICKER>": "US1.AMZN",
    "<PER>": "D",
    "<DATE>": "07/25/19",
    "<TIME>": "00:00:00",
    "<CLOSE>": 1975.02
  },
  {
    "<TICKER>": "US1.AMZN",
    "<PER>": "D",
    "<DATE>": "07/26/19",
    "<TIME>": "00:00:00",
    "<CLOSE>": 1943.05
  },
  {
    "<TICKER>": "US1.AMZN",
    "<PER>": "D",
    "<DATE>": "07/29/19",
    "<TIME>": "00:00:00",
    "<CLOSE>": 1912.87
  },
  {
    "<TICKER>": "US1.AMZN",
    "<PER>": "D",
    "<DATE>": "07/30/19",
    "<TIME>": "00:00:00",
    "<CLOSE>": 1899.22
  },
  {
    "<TICKER>": "US1.AMZN",
    "<PER>": "D",
    "<DATE>": "07/31/19",
    "<TIME>": "00:00:00",
    "<CLOSE>": 1866.39
  },
  {
    "<TICKER>": "US1.AMZN",
    "<PER>": "D",
    "<DATE>": "08/01/19",
    "<TIME>": "00:00:00",
    "<CLOSE>": 1855.33
  },
  {
    "<TICKER>": "US1.AMZN",
    "<PER>": "D",
    "<DATE>": "08/02/19",
    "<TIME>": "00:00:00",
    "<CLOSE>": 1823.52
  },
  {
    "<TICKER>": "US1.AMZN",
    "<PER>": "D",
    "<DATE>": "08/05/19",
    "<TIME>": "00:00:00",
    "<CLOSE>": 1765.13
  },
  {
    "<TICKER>": "US1.AMZN",
    "<PER>": "D",
    "<DATE>": "08/06/19",
    "<TIME>": "00:00:00",
    "<CLOSE>": 1787.44
  },
  {
    "<TICKER>": "US1.AMZN",
    "<PER>": "D",
    "<DATE>": "08/07/19",
    "<TIME>": "00:00:00",
    "<CLOSE>": 1793.39
  },
  {
    "<TICKER>": "US1.AMZN",
    "<PER>": "D",
    "<DATE>": "08/08/19",
    "<TIME>": "00:00:00",
    "<CLOSE>": 1834.26
  },
  {
    "<TICKER>": "US1.AMZN",
    "<PER>": "D",
    "<DATE>": "08/09/19",
    "<TIME>": "00:00:00",
    "<CLOSE>": 1807.88
  },
  {
    "<TICKER>": "US1.AMZN",
    "<PER>": "D",
    "<DATE>": "08/12/19",
    "<TIME>": "00:00:00",
    "<CLOSE>": 1784.75
  },
  {
    "<TICKER>": "US1.AMZN",
    "<PER>": "D",
    "<DATE>": "08/13/19",
    "<TIME>": "00:00:00",
    "<CLOSE>": 1824.29
  },
  {
    "<TICKER>": "US1.AMZN",
    "<PER>": "D",
    "<DATE>": "08/14/19",
    "<TIME>": "00:00:00",
    "<CLOSE>": 1762.96
  },
  {
    "<TICKER>": "US1.AMZN",
    "<PER>": "D",
    "<DATE>": "08/15/19",
    "<TIME>": "00:00:00",
    "<CLOSE>": 1775.41
  },
  {
    "<TICKER>": "US1.AMZN",
    "<PER>": "D",
    "<DATE>": "08/16/19",
    "<TIME>": "00:00:00",
    "<CLOSE>": 1791.8
  },
  {
    "<TICKER>": "US1.AMZN",
    "<PER>": "D",
    "<DATE>": "08/19/19",
    "<TIME>": "00:00:00",
    "<CLOSE>": 1816.83
  },
  {
    "<TICKER>": "US1.AMZN",
    "<PER>": "D",
    "<DATE>": "08/20/19",
    "<TIME>": "00:00:00",
    "<CLOSE>": 1801.35
  },
  {
    "<TICKER>": "US1.AMZN",
    "<PER>": "D",
    "<DATE>": "08/21/19",
    "<TIME>": "00:00:00",
    "<CLOSE>": 1823.38
  },
  {
    "<TICKER>": "US1.AMZN",
    "<PER>": "D",
    "<DATE>": "08/22/19",
    "<TIME>": "00:00:00",
    "<CLOSE>": 1804.25
  },
  {
    "<TICKER>": "US1.AMZN",
    "<PER>": "D",
    "<DATE>": "08/23/19",
    "<TIME>": "00:00:00",
    "<CLOSE>": 1750.77
  },
  {
    "<TICKER>": "US1.AMZN",
    "<PER>": "D",
    "<DATE>": "08/26/19",
    "<TIME>": "00:00:00",
    "<CLOSE>": 1770
  },
  {
    "<TICKER>": "US1.AMZN",
    "<PER>": "D",
    "<DATE>": "08/27/19",
    "<TIME>": "00:00:00",
    "<CLOSE>": 1761.92
  },
  {
    "<TICKER>": "US1.AMZN",
    "<PER>": "D",
    "<DATE>": "08/28/19",
    "<TIME>": "00:00:00",
    "<CLOSE>": 1764
  },
  {
    "<TICKER>": "US1.AMZN",
    "<PER>": "D",
    "<DATE>": "08/29/19",
    "<TIME>": "00:00:00",
    "<CLOSE>": 1786.46
  },
  {
    "<TICKER>": "US1.AMZN",
    "<PER>": "D",
    "<DATE>": "08/30/19",
    "<TIME>": "00:00:00",
    "<CLOSE>": 1776.19
  },
  {
    "<TICKER>": "US1.AMZN",
    "<PER>": "D",
    "<DATE>": "09/03/19",
    "<TIME>": "00:00:00",
    "<CLOSE>": 1789.51
  },
  {
    "<TICKER>": "US1.AMZN",
    "<PER>": "D",
    "<DATE>": "09/04/19",
    "<TIME>": "00:00:00",
    "<CLOSE>": 1800.46
  },
  {
    "<TICKER>": "US1.AMZN",
    "<PER>": "D",
    "<DATE>": "09/05/19",
    "<TIME>": "00:00:00",
    "<CLOSE>": 1840.73
  },
  {
    "<TICKER>": "US1.AMZN",
    "<PER>": "D",
    "<DATE>": "09/06/19",
    "<TIME>": "00:00:00",
    "<CLOSE>": 1833.51
  },
  {
    "<TICKER>": "US1.AMZN",
    "<PER>": "D",
    "<DATE>": "09/09/19",
    "<TIME>": "00:00:00",
    "<CLOSE>": 1831.29
  },
  {
    "<TICKER>": "US1.AMZN",
    "<PER>": "D",
    "<DATE>": "09/10/19",
    "<TIME>": "00:00:00",
    "<CLOSE>": 1821.31
  },
  {
    "<TICKER>": "US1.AMZN",
    "<PER>": "D",
    "<DATE>": "09/11/19",
    "<TIME>": "00:00:00",
    "<CLOSE>": 1822.49
  },
  {
    "<TICKER>": "US1.AMZN",
    "<PER>": "D",
    "<DATE>": "09/12/19",
    "<TIME>": "00:00:00",
    "<CLOSE>": 1843
  },
  {
    "<TICKER>": "US1.AMZN",
    "<PER>": "D",
    "<DATE>": "09/13/19",
    "<TIME>": "00:00:00",
    "<CLOSE>": 1839.34
  },
  {
    "<TICKER>": "US1.AMZN",
    "<PER>": "D",
    "<DATE>": "09/16/19",
    "<TIME>": "00:00:00",
    "<CLOSE>": 1808.23
  },
  {
    "<TICKER>": "US1.AMZN",
    "<PER>": "D",
    "<DATE>": "09/17/19",
    "<TIME>": "00:00:00",
    "<CLOSE>": 1822.62
  },
  {
    "<TICKER>": "US1.AMZN",
    "<PER>": "D",
    "<DATE>": "09/18/19",
    "<TIME>": "00:00:00",
    "<CLOSE>": 1817.59
  },
  {
    "<TICKER>": "US1.AMZN",
    "<PER>": "D",
    "<DATE>": "09/19/19",
    "<TIME>": "00:00:00",
    "<CLOSE>": 1821.54
  },
  {
    "<TICKER>": "US1.AMZN",
    "<PER>": "D",
    "<DATE>": "09/20/19",
    "<TIME>": "00:00:00",
    "<CLOSE>": 1794.91
  },
  {
    "<TICKER>": "US1.AMZN",
    "<PER>": "D",
    "<DATE>": "09/23/19",
    "<TIME>": "00:00:00",
    "<CLOSE>": 1784.29
  },
  {
    "<TICKER>": "US1.AMZN",
    "<PER>": "D",
    "<DATE>": "09/24/19",
    "<TIME>": "00:00:00",
    "<CLOSE>": 1742.34
  },
  {
    "<TICKER>": "US1.AMZN",
    "<PER>": "D",
    "<DATE>": "09/25/19",
    "<TIME>": "00:00:00",
    "<CLOSE>": 1768.08
  },
  {
    "<TICKER>": "US1.AMZN",
    "<PER>": "D",
    "<DATE>": "09/26/19",
    "<TIME>": "00:00:00",
    "<CLOSE>": 1740.12
  },
  {
    "<TICKER>": "US1.AMZN",
    "<PER>": "D",
    "<DATE>": "09/27/19",
    "<TIME>": "00:00:00",
    "<CLOSE>": 1725.85
  },
  {
    "<TICKER>": "US1.AMZN",
    "<PER>": "D",
    "<DATE>": "09/30/19",
    "<TIME>": "00:00:00",
    "<CLOSE>": 1736.12
  },
  {
    "<TICKER>": "US1.AMZN",
    "<PER>": "D",
    "<DATE>": "10/01/19",
    "<TIME>": "00:00:00",
    "<CLOSE>": 1736.11
  },
  {
    "<TICKER>": "US1.AMZN",
    "<PER>": "D",
    "<DATE>": "10/02/19",
    "<TIME>": "00:00:00",
    "<CLOSE>": 1713.23
  },
  {
    "<TICKER>": "US1.AMZN",
    "<PER>": "D",
    "<DATE>": "10/03/19",
    "<TIME>": "00:00:00",
    "<CLOSE>": 1724.25
  },
  {
    "<TICKER>": "US1.AMZN",
    "<PER>": "D",
    "<DATE>": "10/04/19",
    "<TIME>": "00:00:00",
    "<CLOSE>": 1739.4
  },
  {
    "<TICKER>": "US1.AMZN",
    "<PER>": "D",
    "<DATE>": "10/07/19",
    "<TIME>": "00:00:00",
    "<CLOSE>": 1732.5
  },
  {
    "<TICKER>": "US1.AMZN",
    "<PER>": "D",
    "<DATE>": "10/08/19",
    "<TIME>": "00:00:00",
    "<CLOSE>": 1705.25
  },
  {
    "<TICKER>": "US1.AMZN",
    "<PER>": "D",
    "<DATE>": "10/09/19",
    "<TIME>": "00:00:00",
    "<CLOSE>": 1721.79
  },
  {
    "<TICKER>": "US1.AMZN",
    "<PER>": "D",
    "<DATE>": "10/10/19",
    "<TIME>": "00:00:00",
    "<CLOSE>": 1720.56
  },
  {
    "<TICKER>": "US1.AMZN",
    "<PER>": "D",
    "<DATE>": "10/11/19",
    "<TIME>": "00:00:00",
    "<CLOSE>": 1729.98
  },
  {
    "<TICKER>": "US1.AMZN",
    "<PER>": "D",
    "<DATE>": "10/14/19",
    "<TIME>": "00:00:00",
    "<CLOSE>": 1736.5
  },
  {
    "<TICKER>": "US1.AMZN",
    "<PER>": "D",
    "<DATE>": "10/15/19",
    "<TIME>": "00:00:00",
    "<CLOSE>": 1767.35
  },
  {
    "<TICKER>": "US1.AMZN",
    "<PER>": "D",
    "<DATE>": "10/16/19",
    "<TIME>": "00:00:00",
    "<CLOSE>": 1777.42
  },
  {
    "<TICKER>": "US1.AMZN",
    "<PER>": "D",
    "<DATE>": "10/17/19",
    "<TIME>": "00:00:00",
    "<CLOSE>": 1787.47
  },
  {
    "<TICKER>": "US1.AMZN",
    "<PER>": "D",
    "<DATE>": "10/18/19",
    "<TIME>": "00:00:00",
    "<CLOSE>": 1757.79
  },
  {
    "<TICKER>": "US1.AMZN",
    "<PER>": "D",
    "<DATE>": "10/21/19",
    "<TIME>": "00:00:00",
    "<CLOSE>": 1785.835
  },
  {
    "<TICKER>": "US1.AMZN",
    "<PER>": "D",
    "<DATE>": "10/22/19",
    "<TIME>": "00:00:00",
    "<CLOSE>": 1765.34
  },
  {
    "<TICKER>": "US1.AMZN",
    "<PER>": "D",
    "<DATE>": "10/23/19",
    "<TIME>": "00:00:00",
    "<CLOSE>": 1761.99
  },
  {
    "<TICKER>": "US1.AMZN",
    "<PER>": "D",
    "<DATE>": "10/24/19",
    "<TIME>": "00:00:00",
    "<CLOSE>": 1781.5936
  },
  {
    "<TICKER>": "US1.AMZN",
    "<PER>": "D",
    "<DATE>": "10/25/19",
    "<TIME>": "00:00:00",
    "<CLOSE>": 1762
  },
  {
    "<TICKER>": "US1.AMZN",
    "<PER>": "D",
    "<DATE>": "10/28/19",
    "<TIME>": "00:00:00",
    "<CLOSE>": 1777.04
  },
  {
    "<TICKER>": "US1.AMZN",
    "<PER>": "D",
    "<DATE>": "10/29/19",
    "<TIME>": "00:00:00",
    "<CLOSE>": 1763.04
  },
  {
    "<TICKER>": "US1.AMZN",
    "<PER>": "D",
    "<DATE>": "10/30/19",
    "<TIME>": "00:00:00",
    "<CLOSE>": 1780
  },
  {
    "<TICKER>": "US1.AMZN",
    "<PER>": "D",
    "<DATE>": "10/31/19",
    "<TIME>": "00:00:00",
    "<CLOSE>": 1777.143
  },
  {
    "<TICKER>": "US1.AMZN",
    "<PER>": "D",
    "<DATE>": "11/01/19",
    "<TIME>": "00:00:00",
    "<CLOSE>": 1791.47
  },
  {
    "<TICKER>": "US1.AMZN",
    "<PER>": "D",
    "<DATE>": "11/04/19",
    "<TIME>": "00:00:00",
    "<CLOSE>": 1805.27
  },
  {
    "<TICKER>": "US1.AMZN",
    "<PER>": "D",
    "<DATE>": "11/05/19",
    "<TIME>": "00:00:00",
    "<CLOSE>": 1801.7
  },
  {
    "<TICKER>": "US1.AMZN",
    "<PER>": "D",
    "<DATE>": "11/06/19",
    "<TIME>": "00:00:00",
    "<CLOSE>": 1795.94
  },
  {
    "<TICKER>": "US1.AMZN",
    "<PER>": "D",
    "<DATE>": "11/07/19",
    "<TIME>": "00:00:00",
    "<CLOSE>": 1788.2
  },
  {
    "<TICKER>": "US1.AMZN",
    "<PER>": "D",
    "<DATE>": "11/08/19",
    "<TIME>": "00:00:00",
    "<CLOSE>": 1785.88
  },
  {
    "<TICKER>": "US1.AMZN",
    "<PER>": "D",
    "<DATE>": "11/11/19",
    "<TIME>": "00:00:00",
    "<CLOSE>": 1771.9
  },
  {
    "<TICKER>": "US1.AMZN",
    "<PER>": "D",
    "<DATE>": "11/12/19",
    "<TIME>": "00:00:00",
    "<CLOSE>": 1778.23
  },
  {
    "<TICKER>": "US1.AMZN",
    "<PER>": "D",
    "<DATE>": "11/13/19",
    "<TIME>": "00:00:00",
    "<CLOSE>": 1753.4
  },
  {
    "<TICKER>": "US1.AMZN",
    "<PER>": "D",
    "<DATE>": "11/14/19",
    "<TIME>": "00:00:00",
    "<CLOSE>": 1754.65
  },
  {
    "<TICKER>": "US1.AMZN",
    "<PER>": "D",
    "<DATE>": "11/15/19",
    "<TIME>": "00:00:00",
    "<CLOSE>": 1739.08
  },
  {
    "<TICKER>": "US1.AMZN",
    "<PER>": "D",
    "<DATE>": "11/18/19",
    "<TIME>": "00:00:00",
    "<CLOSE>": 1752.86
  },
  {
    "<TICKER>": "US1.AMZN",
    "<PER>": "D",
    "<DATE>": "11/19/19",
    "<TIME>": "00:00:00",
    "<CLOSE>": 1753.16
  },
  {
    "<TICKER>": "US1.AMZN",
    "<PER>": "D",
    "<DATE>": "11/20/19",
    "<TIME>": "00:00:00",
    "<CLOSE>": 1746.6336
  },
  {
    "<TICKER>": "US1.AMZN",
    "<PER>": "D",
    "<DATE>": "11/21/19",
    "<TIME>": "00:00:00",
    "<CLOSE>": 1735
  },
  {
    "<TICKER>": "US1.AMZN",
    "<PER>": "D",
    "<DATE>": "11/22/19",
    "<TIME>": "00:00:00",
    "<CLOSE>": 1745.85
  },
  {
    "<TICKER>": "US1.AMZN",
    "<PER>": "D",
    "<DATE>": "11/25/19",
    "<TIME>": "00:00:00",
    "<CLOSE>": 1773.69
  },
  {
    "<TICKER>": "US1.AMZN",
    "<PER>": "D",
    "<DATE>": "11/26/19",
    "<TIME>": "00:00:00",
    "<CLOSE>": 1796.99
  },
  {
    "<TICKER>": "US1.AMZN",
    "<PER>": "D",
    "<DATE>": "11/27/19",
    "<TIME>": "00:00:00",
    "<CLOSE>": 1818.23
  },
  {
    "<TICKER>": "US1.AMZN",
    "<PER>": "D",
    "<DATE>": "11/29/19",
    "<TIME>": "00:00:00",
    "<CLOSE>": 1798.75
  },
  {
    "<TICKER>": "US1.AMZN",
    "<PER>": "D",
    "<DATE>": "12/02/19",
    "<TIME>": "00:00:00",
    "<CLOSE>": 1781.61
  },
  {
    "<TICKER>": "US1.AMZN",
    "<PER>": "D",
    "<DATE>": "12/03/19",
    "<TIME>": "00:00:00",
    "<CLOSE>": 1770.33
  },
  {
    "<TICKER>": "US1.AMZN",
    "<PER>": "D",
    "<DATE>": "12/04/19",
    "<TIME>": "00:00:00",
    "<CLOSE>": 1760.48
  },
  {
    "<TICKER>": "US1.AMZN",
    "<PER>": "D",
    "<DATE>": "12/05/19",
    "<TIME>": "00:00:00",
    "<CLOSE>": 1740.48
  },
  {
    "<TICKER>": "US1.AMZN",
    "<PER>": "D",
    "<DATE>": "12/06/19",
    "<TIME>": "00:00:00",
    "<CLOSE>": 1751.59
  },
  {
    "<TICKER>": "US1.AMZN",
    "<PER>": "D",
    "<DATE>": "12/09/19",
    "<TIME>": "00:00:00",
    "<CLOSE>": 1749.42
  },
  {
    "<TICKER>": "US1.AMZN",
    "<PER>": "D",
    "<DATE>": "12/10/19",
    "<TIME>": "00:00:00",
    "<CLOSE>": 1739.49
  },
  {
    "<TICKER>": "US1.AMZN",
    "<PER>": "D",
    "<DATE>": "12/11/19",
    "<TIME>": "00:00:00",
    "<CLOSE>": 1748.9
  },
  {
    "<TICKER>": "US1.AMZN",
    "<PER>": "D",
    "<DATE>": "12/12/19",
    "<TIME>": "00:00:00",
    "<CLOSE>": 1760.18
  },
  {
    "<TICKER>": "US1.AMZN",
    "<PER>": "D",
    "<DATE>": "12/13/19",
    "<TIME>": "00:00:00",
    "<CLOSE>": 1760.93
  },
  {
    "<TICKER>": "US1.AMZN",
    "<PER>": "D",
    "<DATE>": "12/16/19",
    "<TIME>": "00:00:00",
    "<CLOSE>": 1769.21
  },
  {
    "<TICKER>": "US1.AMZN",
    "<PER>": "D",
    "<DATE>": "12/17/19",
    "<TIME>": "00:00:00",
    "<CLOSE>": 1790.66
  },
  {
    "<TICKER>": "US1.AMZN",
    "<PER>": "D",
    "<DATE>": "12/18/19",
    "<TIME>": "00:00:00",
    "<CLOSE>": 1782.36
  },
  {
    "<TICKER>": "US1.AMZN",
    "<PER>": "D",
    "<DATE>": "12/19/19",
    "<TIME>": "00:00:00",
    "<CLOSE>": 1792.29
  },
  {
    "<TICKER>": "US1.AMZN",
    "<PER>": "D",
    "<DATE>": "12/20/19",
    "<TIME>": "00:00:00",
    "<CLOSE>": 1786.57
  },
  {
    "<TICKER>": "US1.AMZN",
    "<PER>": "D",
    "<DATE>": "12/23/19",
    "<TIME>": "00:00:00",
    "<CLOSE>": 1793
  },
  {
    "<TICKER>": "US1.AMZN",
    "<PER>": "D",
    "<DATE>": "12/24/19",
    "<TIME>": "00:00:00",
    "<CLOSE>": 1789.21
  },
  {
    "<TICKER>": "US1.AMZN",
    "<PER>": "D",
    "<DATE>": "12/26/19",
    "<TIME>": "00:00:00",
    "<CLOSE>": 1869.02
  },
  {
    "<TICKER>": "US1.AMZN",
    "<PER>": "D",
    "<DATE>": "12/27/19",
    "<TIME>": "00:00:00",
    "<CLOSE>": 1869.26
  },
  {
    "<TICKER>": "US1.AMZN",
    "<PER>": "D",
    "<DATE>": "12/30/19",
    "<TIME>": "00:00:00",
    "<CLOSE>": 1847.18
  },
  {
    "<TICKER>": "US1.AMZN",
    "<PER>": "D",
    "<DATE>": "12/31/19",
    "<TIME>": "00:00:00",
    "<CLOSE>": 1847.64
  }
]