[
  {
    "<TICKER>": "VSAT US",
    "<PER>": "D",
    "<DATE>": "01/01/20",
    "<TIME>": "00:00",
    "<CLOSE>": 4541.15687
  },
  {
    "<TICKER>": "VSAT US",
    "<PER>": "D",
    "<DATE>": "01/02/20",
    "<TIME>": "00:00",
    "<CLOSE>": 4547.9648
  },
  {
    "<TICKER>": "VSAT US",
    "<PER>": "D",
    "<DATE>": "01/03/20",
    "<TIME>": "00:00",
    "<CLOSE>": 4558.92514
  },
  {
    "<TICKER>": "VSAT US",
    "<PER>": "D",
    "<DATE>": "01/06/20",
    "<TIME>": "00:00",
    "<CLOSE>": 4546.85403
  },
  {
    "<TICKER>": "VSAT US",
    "<PER>": "D",
    "<DATE>": "01/07/20",
    "<TIME>": "00:00",
    "<CLOSE>": 4487.14264
  },
  {
    "<TICKER>": "VSAT US",
    "<PER>": "D",
    "<DATE>": "01/08/20",
    "<TIME>": "00:00",
    "<CLOSE>": 4293.4052
  },
  {
    "<TICKER>": "VSAT US",
    "<PER>": "D",
    "<DATE>": "01/09/20",
    "<TIME>": "00:00",
    "<CLOSE>": 4325.69998
  },
  {
    "<TICKER>": "VSAT US",
    "<PER>": "D",
    "<DATE>": "01/10/20",
    "<TIME>": "00:00",
    "<CLOSE>": 4308.55258
  },
  {
    "<TICKER>": "VSAT US",
    "<PER>": "D",
    "<DATE>": "01/13/20",
    "<TIME>": "00:00",
    "<CLOSE>": 4413.61592
  },
  {
    "<TICKER>": "VSAT US",
    "<PER>": "D",
    "<DATE>": "01/14/20",
    "<TIME>": "00:00",
    "<CLOSE>": 4452.24673
  },
  {
    "<TICKER>": "VSAT US",
    "<PER>": "D",
    "<DATE>": "01/15/20",
    "<TIME>": "00:00",
    "<CLOSE>": 4485.60269
  },
  {
    "<TICKER>": "VSAT US",
    "<PER>": "D",
    "<DATE>": "01/16/20",
    "<TIME>": "00:00",
    "<CLOSE>": 4530.23865
  },
  {
    "<TICKER>": "VSAT US",
    "<PER>": "D",
    "<DATE>": "01/17/20",
    "<TIME>": "00:00",
    "<CLOSE>": 4480.77636
  },
  {
    "<TICKER>": "VSAT US",
    "<PER>": "D",
    "<DATE>": "01/20/20",
    "<TIME>": "00:00",
    "<CLOSE>": 4480.77636
  },
  {
    "<TICKER>": "VSAT US",
    "<PER>": "D",
    "<DATE>": "01/21/20",
    "<TIME>": "00:00",
    "<CLOSE>": 4424.64401
  },
  {
    "<TICKER>": "VSAT US",
    "<PER>": "D",
    "<DATE>": "01/22/20",
    "<TIME>": "00:00",
    "<CLOSE>": 4344.53863
  },
  {
    "<TICKER>": "VSAT US",
    "<PER>": "D",
    "<DATE>": "01/23/20",
    "<TIME>": "00:00",
    "<CLOSE>": 4306.95297
  },
  {
    "<TICKER>": "VSAT US",
    "<PER>": "D",
    "<DATE>": "01/24/20",
    "<TIME>": "00:00",
    "<CLOSE>": 4293.84677
  },
  {
    "<TICKER>": "VSAT US",
    "<PER>": "D",
    "<DATE>": "01/27/20",
    "<TIME>": "00:00",
    "<CLOSE>": 4311.68599
  },
  {
    "<TICKER>": "VSAT US",
    "<PER>": "D",
    "<DATE>": "01/28/20",
    "<TIME>": "00:00",
    "<CLOSE>": 4280.84342
  },
  {
    "<TICKER>": "VSAT US",
    "<PER>": "D",
    "<DATE>": "01/29/20",
    "<TIME>": "00:00",
    "<CLOSE>": 4229.48925
  },
  {
    "<TICKER>": "VSAT US",
    "<PER>": "D",
    "<DATE>": "01/30/20",
    "<TIME>": "00:00",
    "<CLOSE>": 4156.06577
  },
  {
    "<TICKER>": "VSAT US",
    "<PER>": "D",
    "<DATE>": "01/31/20",
    "<TIME>": "00:00",
    "<CLOSE>": 4061.90749
  },
  {
    "<TICKER>": "VSAT US",
    "<PER>": "D",
    "<DATE>": "02/03/20",
    "<TIME>": "00:00",
    "<CLOSE>": 4158.782
  },
  {
    "<TICKER>": "VSAT US",
    "<PER>": "D",
    "<DATE>": "02/04/20",
    "<TIME>": "00:00",
    "<CLOSE>": 4170.82175
  },
  {
    "<TICKER>": "VSAT US",
    "<PER>": "D",
    "<DATE>": "02/05/20",
    "<TIME>": "00:00",
    "<CLOSE>": 4191.67412
  },
  {
    "<TICKER>": "VSAT US",
    "<PER>": "D",
    "<DATE>": "02/06/20",
    "<TIME>": "00:00",
    "<CLOSE>": 4207.97593
  },
  {
    "<TICKER>": "VSAT US",
    "<PER>": "D",
    "<DATE>": "02/07/20",
    "<TIME>": "00:00",
    "<CLOSE>": 4203.28887
  },
  {
    "<TICKER>": "VSAT US",
    "<PER>": "D",
    "<DATE>": "02/10/20",
    "<TIME>": "00:00",
    "<CLOSE>": 4154.7004
  },
  {
    "<TICKER>": "VSAT US",
    "<PER>": "D",
    "<DATE>": "02/11/20",
    "<TIME>": "00:00",
    "<CLOSE>": 4113.8175
  },
  {
    "<TICKER>": "VSAT US",
    "<PER>": "D",
    "<DATE>": "02/12/20",
    "<TIME>": "00:00",
    "<CLOSE>": 4100.87524
  },
  {
    "<TICKER>": "VSAT US",
    "<PER>": "D",
    "<DATE>": "02/13/20",
    "<TIME>": "00:00",
    "<CLOSE>": 3972.62256
  },
  {
    "<TICKER>": "VSAT US",
    "<PER>": "D",
    "<DATE>": "02/14/20",
    "<TIME>": "00:00",
    "<CLOSE>": 3881.1311
  },
  {
    "<TICKER>": "VSAT US",
    "<PER>": "D",
    "<DATE>": "02/17/20",
    "<TIME>": "00:00",
    "<CLOSE>": 3881.1311
  },
  {
    "<TICKER>": "VSAT US",
    "<PER>": "D",
    "<DATE>": "02/18/20",
    "<TIME>": "00:00",
    "<CLOSE>": 3703.83948
  },
  {
    "<TICKER>": "VSAT US",
    "<PER>": "D",
    "<DATE>": "02/19/20",
    "<TIME>": "00:00",
    "<CLOSE>": 3628.63648
  },
  {
    "<TICKER>": "VSAT US",
    "<PER>": "D",
    "<DATE>": "02/20/20",
    "<TIME>": "00:00",
    "<CLOSE>": 3710.83729
  },
  {
    "<TICKER>": "VSAT US",
    "<PER>": "D",
    "<DATE>": "02/21/20",
    "<TIME>": "00:00",
    "<CLOSE>": 3563.61484
  },
  {
    "<TICKER>": "VSAT US",
    "<PER>": "D",
    "<DATE>": "02/24/20",
    "<TIME>": "00:00",
    "<CLOSE>": 3534.55909
  },
  {
    "<TICKER>": "VSAT US",
    "<PER>": "D",
    "<DATE>": "02/25/20",
    "<TIME>": "00:00",
    "<CLOSE>": 3681.30971
  },
  {
    "<TICKER>": "VSAT US",
    "<PER>": "D",
    "<DATE>": "02/26/20",
    "<TIME>": "00:00",
    "<CLOSE>": 3726.37094
  },
  {
    "<TICKER>": "VSAT US",
    "<PER>": "D",
    "<DATE>": "02/27/20",
    "<TIME>": "00:00",
    "<CLOSE>": 3754.6672
  },
  {
    "<TICKER>": "VSAT US",
    "<PER>": "D",
    "<DATE>": "02/28/20",
    "<TIME>": "00:00",
    "<CLOSE>": 3856.9275
  },
  {
    "<TICKER>": "VSAT US",
    "<PER>": "D",
    "<DATE>": "03/02/20",
    "<TIME>": "00:00",
    "<CLOSE>": 3929.79948
  },
  {
    "<TICKER>": "VSAT US",
    "<PER>": "D",
    "<DATE>": "03/03/20",
    "<TIME>": "00:00",
    "<CLOSE>": 3884.25074
  },
  {
    "<TICKER>": "VSAT US",
    "<PER>": "D",
    "<DATE>": "03/04/20",
    "<TIME>": "00:00",
    "<CLOSE>": 3810.41991
  },
  {
    "<TICKER>": "VSAT US",
    "<PER>": "D",
    "<DATE>": "03/05/20",
    "<TIME>": "00:00",
    "<CLOSE>": 3649.37044
  },
  {
    "<TICKER>": "VSAT US",
    "<PER>": "D",
    "<DATE>": "03/06/20",
    "<TIME>": "00:00",
    "<CLOSE>": 3558.81038
  },
  {
    "<TICKER>": "VSAT US",
    "<PER>": "D",
    "<DATE>": "03/09/20",
    "<TIME>": "00:00",
    "<CLOSE>": 3565.63496
  },
  {
    "<TICKER>": "VSAT US",
    "<PER>": "D",
    "<DATE>": "03/10/20",
    "<TIME>": "00:00",
    "<CLOSE>": 3586.515
  },
  {
    "<TICKER>": "VSAT US",
    "<PER>": "D",
    "<DATE>": "03/11/20",
    "<TIME>": "00:00",
    "<CLOSE>": 3469.31719
  },
  {
    "<TICKER>": "VSAT US",
    "<PER>": "D",
    "<DATE>": "03/12/20",
    "<TIME>": "00:00",
    "<CLOSE>": 3200.7221
  },
  {
    "<TICKER>": "VSAT US",
    "<PER>": "D",
    "<DATE>": "03/13/20",
    "<TIME>": "00:00",
    "<CLOSE>": 3146.26324
  },
  {
    "<TICKER>": "VSAT US",
    "<PER>": "D",
    "<DATE>": "03/16/20",
    "<TIME>": "00:00",
    "<CLOSE>": 2826.83618
  },
  {
    "<TICKER>": "VSAT US",
    "<PER>": "D",
    "<DATE>": "03/17/20",
    "<TIME>": "00:00",
    "<CLOSE>": 2994.13819
  },
  {
    "<TICKER>": "VSAT US",
    "<PER>": "D",
    "<DATE>": "03/18/20",
    "<TIME>": "00:00",
    "<CLOSE>": 2448.90342
  },
  {
    "<TICKER>": "VSAT US",
    "<PER>": "D",
    "<DATE>": "03/19/20",
    "<TIME>": "00:00",
    "<CLOSE>": 2525.44203
  },
  {
    "<TICKER>": "VSAT US",
    "<PER>": "D",
    "<DATE>": "03/20/20",
    "<TIME>": "00:00",
    "<CLOSE>": 2246.28096
  },
  {
    "<TICKER>": "VSAT US",
    "<PER>": "D",
    "<DATE>": "03/23/20",
    "<TIME>": "00:00",
    "<CLOSE>": 2192.38169
  },
  {
    "<TICKER>": "VSAT US",
    "<PER>": "D",
    "<DATE>": "03/24/20",
    "<TIME>": "00:00",
    "<CLOSE>": 2805.90138
  },
  {
    "<TICKER>": "VSAT US",
    "<PER>": "D",
    "<DATE>": "03/25/20",
    "<TIME>": "00:00",
    "<CLOSE>": 3000.31104
  },
  {
    "<TICKER>": "VSAT US",
    "<PER>": "D",
    "<DATE>": "03/26/20",
    "<TIME>": "00:00",
    "<CLOSE>": 3133.52649
  },
  {
    "<TICKER>": "VSAT US",
    "<PER>": "D",
    "<DATE>": "03/27/20",
    "<TIME>": "00:00",
    "<CLOSE>": 3050.97375
  },
  {
    "<TICKER>": "VSAT US",
    "<PER>": "D",
    "<DATE>": "03/30/20",
    "<TIME>": "00:00",
    "<CLOSE>": 3070.73734
  },
  {
    "<TICKER>": "VSAT US",
    "<PER>": "D",
    "<DATE>": "03/31/20",
    "<TIME>": "00:00",
    "<CLOSE>": 2805.34122
  },
  {
    "<TICKER>": "VSAT US",
    "<PER>": "D",
    "<DATE>": "04/01/20",
    "<TIME>": "00:00",
    "<CLOSE>": 2591.95894
  },
  {
    "<TICKER>": "VSAT US",
    "<PER>": "D",
    "<DATE>": "04/02/20",
    "<TIME>": "00:00",
    "<CLOSE>": 2651.05891
  },
  {
    "<TICKER>": "VSAT US",
    "<PER>": "D",
    "<DATE>": "04/03/20",
    "<TIME>": "00:00",
    "<CLOSE>": 2536.30248
  },
  {
    "<TICKER>": "VSAT US",
    "<PER>": "D",
    "<DATE>": "04/06/20",
    "<TIME>": "00:00",
    "<CLOSE>": 2885.33768
  },
  {
    "<TICKER>": "VSAT US",
    "<PER>": "D",
    "<DATE>": "04/07/20",
    "<TIME>": "00:00",
    "<CLOSE>": 2982.93425
  },
  {
    "<TICKER>": "VSAT US",
    "<PER>": "D",
    "<DATE>": "04/08/20",
    "<TIME>": "00:00",
    "<CLOSE>": 3253.8782
  },
  {
    "<TICKER>": "VSAT US",
    "<PER>": "D",
    "<DATE>": "04/09/20",
    "<TIME>": "00:00",
    "<CLOSE>": 3295.24396
  },
  {
    "<TICKER>": "VSAT US",
    "<PER>": "D",
    "<DATE>": "04/10/20",
    "<TIME>": "00:00",
    "<CLOSE>": 3295.24396
  },
  {
    "<TICKER>": "VSAT US",
    "<PER>": "D",
    "<DATE>": "04/13/20",
    "<TIME>": "00:00",
    "<CLOSE>": 3086.54026
  },
  {
    "<TICKER>": "VSAT US",
    "<PER>": "D",
    "<DATE>": "04/14/20",
    "<TIME>": "00:00",
    "<CLOSE>": 3154.4565
  },
  {
    "<TICKER>": "VSAT US",
    "<PER>": "D",
    "<DATE>": "04/15/20",
    "<TIME>": "00:00",
    "<CLOSE>": 3027.57126
  },
  {
    "<TICKER>": "VSAT US",
    "<PER>": "D",
    "<DATE>": "04/16/20",
    "<TIME>": "00:00",
    "<CLOSE>": 2915.0268
  },
  {
    "<TICKER>": "VSAT US",
    "<PER>": "D",
    "<DATE>": "04/17/20",
    "<TIME>": "00:00",
    "<CLOSE>": 3039.30732
  },
  {
    "<TICKER>": "VSAT US",
    "<PER>": "D",
    "<DATE>": "04/20/20",
    "<TIME>": "00:00",
    "<CLOSE>": 3118.58305
  },
  {
    "<TICKER>": "VSAT US",
    "<PER>": "D",
    "<DATE>": "04/21/20",
    "<TIME>": "00:00",
    "<CLOSE>": 3034.1231
  },
  {
    "<TICKER>": "VSAT US",
    "<PER>": "D",
    "<DATE>": "04/22/20",
    "<TIME>": "00:00",
    "<CLOSE>": 3099.18012
  },
  {
    "<TICKER>": "VSAT US",
    "<PER>": "D",
    "<DATE>": "04/23/20",
    "<TIME>": "00:00",
    "<CLOSE>": 3100.63886
  },
  {
    "<TICKER>": "VSAT US",
    "<PER>": "D",
    "<DATE>": "04/24/20",
    "<TIME>": "00:00",
    "<CLOSE>": 3084.87872
  },
  {
    "<TICKER>": "VSAT US",
    "<PER>": "D",
    "<DATE>": "04/27/20",
    "<TIME>": "00:00",
    "<CLOSE>": 3170.07272
  },
  {
    "<TICKER>": "VSAT US",
    "<PER>": "D",
    "<DATE>": "04/28/20",
    "<TIME>": "00:00",
    "<CLOSE>": 3188.79511
  },
  {
    "<TICKER>": "VSAT US",
    "<PER>": "D",
    "<DATE>": "04/29/20",
    "<TIME>": "00:00",
    "<CLOSE>": 3336.72425
  },
  {
    "<TICKER>": "VSAT US",
    "<PER>": "D",
    "<DATE>": "04/30/20",
    "<TIME>": "00:00",
    "<CLOSE>": 3157.316
  },
  {
    "<TICKER>": "VSAT US",
    "<PER>": "D",
    "<DATE>": "05/01/20",
    "<TIME>": "00:00",
    "<CLOSE>": 3058.1538
  },
  {
    "<TICKER>": "VSAT US",
    "<PER>": "D",
    "<DATE>": "05/04/20",
    "<TIME>": "00:00",
    "<CLOSE>": 2963.94358
  },
  {
    "<TICKER>": "VSAT US",
    "<PER>": "D",
    "<DATE>": "05/05/20",
    "<TIME>": "00:00",
    "<CLOSE>": 2939.5018
  },
  {
    "<TICKER>": "VSAT US",
    "<PER>": "D",
    "<DATE>": "05/06/20",
    "<TIME>": "00:00",
    "<CLOSE>": 2820.65086
  },
  {
    "<TICKER>": "VSAT US",
    "<PER>": "D",
    "<DATE>": "05/07/20",
    "<TIME>": "00:00",
    "<CLOSE>": 2905.12411
  },
  {
    "<TICKER>": "VSAT US",
    "<PER>": "D",
    "<DATE>": "05/08/20",
    "<TIME>": "00:00",
    "<CLOSE>": 3030.8808
  },
  {
    "<TICKER>": "VSAT US",
    "<PER>": "D",
    "<DATE>": "05/11/20",
    "<TIME>": "00:00",
    "<CLOSE>": 2865.73868
  },
  {
    "<TICKER>": "VSAT US",
    "<PER>": "D",
    "<DATE>": "05/12/20",
    "<TIME>": "00:00",
    "<CLOSE>": 2699.41318
  },
  {
    "<TICKER>": "VSAT US",
    "<PER>": "D",
    "<DATE>": "05/13/20",
    "<TIME>": "00:00",
    "<CLOSE>": 2591.58075
  },
  {
    "<TICKER>": "VSAT US",
    "<PER>": "D",
    "<DATE>": "05/14/20",
    "<TIME>": "00:00",
    "<CLOSE>": 2551.94247
  },
  {
    "<TICKER>": "VSAT US",
    "<PER>": "D",
    "<DATE>": "05/15/20",
    "<TIME>": "00:00",
    "<CLOSE>": 2585.53269
  },
  {
    "<TICKER>": "VSAT US",
    "<PER>": "D",
    "<DATE>": "05/18/20",
    "<TIME>": "00:00",
    "<CLOSE>": 2814.27403
  },
  {
    "<TICKER>": "VSAT US",
    "<PER>": "D",
    "<DATE>": "05/19/20",
    "<TIME>": "00:00",
    "<CLOSE>": 2757.72989
  },
  {
    "<TICKER>": "VSAT US",
    "<PER>": "D",
    "<DATE>": "05/20/20",
    "<TIME>": "00:00",
    "<CLOSE>": 2914.97692
  },
  {
    "<TICKER>": "VSAT US",
    "<PER>": "D",
    "<DATE>": "05/21/20",
    "<TIME>": "00:00",
    "<CLOSE>": 2972.833
  },
  {
    "<TICKER>": "VSAT US",
    "<PER>": "D",
    "<DATE>": "05/22/20",
    "<TIME>": "00:00",
    "<CLOSE>": 3024.03067
  },
  {
    "<TICKER>": "VSAT US",
    "<PER>": "D",
    "<DATE>": "05/25/20",
    "<TIME>": "00:00",
    "<CLOSE>": 3024.03067
  },
  {
    "<TICKER>": "VSAT US",
    "<PER>": "D",
    "<DATE>": "05/26/20",
    "<TIME>": "00:00",
    "<CLOSE>": 3376.00972
  },
  {
    "<TICKER>": "VSAT US",
    "<PER>": "D",
    "<DATE>": "05/27/20",
    "<TIME>": "00:00",
    "<CLOSE>": 3130.38969
  },
  {
    "<TICKER>": "VSAT US",
    "<PER>": "D",
    "<DATE>": "05/28/20",
    "<TIME>": "00:00",
    "<CLOSE>": 3016.7586
  },
  {
    "<TICKER>": "VSAT US",
    "<PER>": "D",
    "<DATE>": "05/29/20",
    "<TIME>": "00:00",
    "<CLOSE>": 2959.5006
  },
  {
    "<TICKER>": "VSAT US",
    "<PER>": "D",
    "<DATE>": "06/01/20",
    "<TIME>": "00:00",
    "<CLOSE>": 3006.34991
  },
  {
    "<TICKER>": "VSAT US",
    "<PER>": "D",
    "<DATE>": "06/02/20",
    "<TIME>": "00:00",
    "<CLOSE>": 3009.43885
  },
  {
    "<TICKER>": "VSAT US",
    "<PER>": "D",
    "<DATE>": "06/03/20",
    "<TIME>": "00:00",
    "<CLOSE>": 3104.39852
  },
  {
    "<TICKER>": "VSAT US",
    "<PER>": "D",
    "<DATE>": "06/04/20",
    "<TIME>": "00:00",
    "<CLOSE>": 3109.60048
  },
  {
    "<TICKER>": "VSAT US",
    "<PER>": "D",
    "<DATE>": "06/05/20",
    "<TIME>": "00:00",
    "<CLOSE>": 3115.6513
  },
  {
    "<TICKER>": "VSAT US",
    "<PER>": "D",
    "<DATE>": "06/08/20",
    "<TIME>": "00:00",
    "<CLOSE>": 3242.18601
  },
  {
    "<TICKER>": "VSAT US",
    "<PER>": "D",
    "<DATE>": "06/09/20",
    "<TIME>": "00:00",
    "<CLOSE>": 3163.6625
  },
  {
    "<TICKER>": "VSAT US",
    "<PER>": "D",
    "<DATE>": "06/10/20",
    "<TIME>": "00:00",
    "<CLOSE>": 2898.48346
  },
  {
    "<TICKER>": "VSAT US",
    "<PER>": "D",
    "<DATE>": "06/11/20",
    "<TIME>": "00:00",
    "<CLOSE>": 2774.25179
  },
  {
    "<TICKER>": "VSAT US",
    "<PER>": "D",
    "<DATE>": "06/12/20",
    "<TIME>": "00:00",
    "<CLOSE>": 2799.62407
  },
  {
    "<TICKER>": "VSAT US",
    "<PER>": "D",
    "<DATE>": "06/15/20",
    "<TIME>": "00:00",
    "<CLOSE>": 2814.24882
  },
  {
    "<TICKER>": "VSAT US",
    "<PER>": "D",
    "<DATE>": "06/16/20",
    "<TIME>": "00:00",
    "<CLOSE>": 2967.1044
  },
  {
    "<TICKER>": "VSAT US",
    "<PER>": "D",
    "<DATE>": "06/17/20",
    "<TIME>": "00:00",
    "<CLOSE>": 2879.6941
  },
  {
    "<TICKER>": "VSAT US",
    "<PER>": "D",
    "<DATE>": "06/18/20",
    "<TIME>": "00:00",
    "<CLOSE>": 2868.51629
  },
  {
    "<TICKER>": "VSAT US",
    "<PER>": "D",
    "<DATE>": "06/19/20",
    "<TIME>": "00:00",
    "<CLOSE>": 2805.27023
  },
  {
    "<TICKER>": "VSAT US",
    "<PER>": "D",
    "<DATE>": "06/22/20",
    "<TIME>": "00:00",
    "<CLOSE>": 2723.17011
  },
  {
    "<TICKER>": "VSAT US",
    "<PER>": "D",
    "<DATE>": "06/23/20",
    "<TIME>": "00:00",
    "<CLOSE>": 2777.2703
  },
  {
    "<TICKER>": "VSAT US",
    "<PER>": "D",
    "<DATE>": "06/24/20",
    "<TIME>": "00:00",
    "<CLOSE>": 2678.1972
  },
  {
    "<TICKER>": "VSAT US",
    "<PER>": "D",
    "<DATE>": "06/25/20",
    "<TIME>": "00:00",
    "<CLOSE>": 2667.18586
  },
  {
    "<TICKER>": "VSAT US",
    "<PER>": "D",
    "<DATE>": "06/26/20",
    "<TIME>": "00:00",
    "<CLOSE>": 2565.25808
  },
  {
    "<TICKER>": "VSAT US",
    "<PER>": "D",
    "<DATE>": "06/29/20",
    "<TIME>": "00:00",
    "<CLOSE>": 2760.84408
  },
  {
    "<TICKER>": "VSAT US",
    "<PER>": "D",
    "<DATE>": "06/30/20",
    "<TIME>": "00:00",
    "<CLOSE>": 2730.86197
  },
  {
    "<TICKER>": "VSAT US",
    "<PER>": "D",
    "<DATE>": "07/01/20",
    "<TIME>": "00:00",
    "<CLOSE>": 2600.12804
  },
  {
    "<TICKER>": "VSAT US",
    "<PER>": "D",
    "<DATE>": "07/02/20",
    "<TIME>": "00:00",
    "<CLOSE>": 2585.34212
  },
  {
    "<TICKER>": "VSAT US",
    "<PER>": "D",
    "<DATE>": "07/03/20",
    "<TIME>": "00:00",
    "<CLOSE>": 2585.34212
  },
  {
    "<TICKER>": "VSAT US",
    "<PER>": "D",
    "<DATE>": "07/06/20",
    "<TIME>": "00:00",
    "<CLOSE>": 2687.56021
  },
  {
    "<TICKER>": "VSAT US",
    "<PER>": "D",
    "<DATE>": "07/07/20",
    "<TIME>": "00:00",
    "<CLOSE>": 2608.62945
  },
  {
    "<TICKER>": "VSAT US",
    "<PER>": "D",
    "<DATE>": "07/08/20",
    "<TIME>": "00:00",
    "<CLOSE>": 2675.03746
  },
  {
    "<TICKER>": "VSAT US",
    "<PER>": "D",
    "<DATE>": "07/09/20",
    "<TIME>": "00:00",
    "<CLOSE>": 2563.84798
  },
  {
    "<TICKER>": "VSAT US",
    "<PER>": "D",
    "<DATE>": "07/10/20",
    "<TIME>": "00:00",
    "<CLOSE>": 2620.93531
  },
  {
    "<TICKER>": "VSAT US",
    "<PER>": "D",
    "<DATE>": "07/13/20",
    "<TIME>": "00:00",
    "<CLOSE>": 2581.22441
  },
  {
    "<TICKER>": "VSAT US",
    "<PER>": "D",
    "<DATE>": "07/14/20",
    "<TIME>": "00:00",
    "<CLOSE>": 2620.05305
  },
  {
    "<TICKER>": "VSAT US",
    "<PER>": "D",
    "<DATE>": "07/15/20",
    "<TIME>": "00:00",
    "<CLOSE>": 2721.7606
  },
  {
    "<TICKER>": "VSAT US",
    "<PER>": "D",
    "<DATE>": "07/16/20",
    "<TIME>": "00:00",
    "<CLOSE>": 2711.93357
  },
  {
    "<TICKER>": "VSAT US",
    "<PER>": "D",
    "<DATE>": "07/17/20",
    "<TIME>": "00:00",
    "<CLOSE>": 2700.48377
  },
  {
    "<TICKER>": "VSAT US",
    "<PER>": "D",
    "<DATE>": "07/20/20",
    "<TIME>": "00:00",
    "<CLOSE>": 2695.0539
  },
  {
    "<TICKER>": "VSAT US",
    "<PER>": "D",
    "<DATE>": "07/21/20",
    "<TIME>": "00:00",
    "<CLOSE>": 2720.32663
  },
  {
    "<TICKER>": "VSAT US",
    "<PER>": "D",
    "<DATE>": "07/22/20",
    "<TIME>": "00:00",
    "<CLOSE>": 2713.47392
  },
  {
    "<TICKER>": "VSAT US",
    "<PER>": "D",
    "<DATE>": "07/23/20",
    "<TIME>": "00:00",
    "<CLOSE>": 2711.89199
  },
  {
    "<TICKER>": "VSAT US",
    "<PER>": "D",
    "<DATE>": "07/24/20",
    "<TIME>": "00:00",
    "<CLOSE>": 2680.72165
  },
  {
    "<TICKER>": "VSAT US",
    "<PER>": "D",
    "<DATE>": "07/27/20",
    "<TIME>": "00:00",
    "<CLOSE>": 2687.412
  },
  {
    "<TICKER>": "VSAT US",
    "<PER>": "D",
    "<DATE>": "07/28/20",
    "<TIME>": "00:00",
    "<CLOSE>": 2795.4699
  },
  {
    "<TICKER>": "VSAT US",
    "<PER>": "D",
    "<DATE>": "07/29/20",
    "<TIME>": "00:00",
    "<CLOSE>": 2820.52836
  },
  {
    "<TICKER>": "VSAT US",
    "<PER>": "D",
    "<DATE>": "07/30/20",
    "<TIME>": "00:00",
    "<CLOSE>": 2819.19744
  },
  {
    "<TICKER>": "VSAT US",
    "<PER>": "D",
    "<DATE>": "07/31/20",
    "<TIME>": "00:00",
    "<CLOSE>": 2820.0522
  },
  {
    "<TICKER>": "VSAT US",
    "<PER>": "D",
    "<DATE>": "08/03/20",
    "<TIME>": "00:00",
    "<CLOSE>": 2749.6125
  },
  {
    "<TICKER>": "VSAT US",
    "<PER>": "D",
    "<DATE>": "08/04/20",
    "<TIME>": "00:00",
    "<CLOSE>": 2820.84633
  },
  {
    "<TICKER>": "VSAT US",
    "<PER>": "D",
    "<DATE>": "08/05/20",
    "<TIME>": "00:00",
    "<CLOSE>": 2765.6096
  },
  {
    "<TICKER>": "VSAT US",
    "<PER>": "D",
    "<DATE>": "08/06/20",
    "<TIME>": "00:00",
    "<CLOSE>": 2828.02954
  },
  {
    "<TICKER>": "VSAT US",
    "<PER>": "D",
    "<DATE>": "08/07/20",
    "<TIME>": "00:00",
    "<CLOSE>": 3107.36732
  },
  {
    "<TICKER>": "VSAT US",
    "<PER>": "D",
    "<DATE>": "08/10/20",
    "<TIME>": "00:00",
    "<CLOSE>": 3070.41403
  },
  {
    "<TICKER>": "VSAT US",
    "<PER>": "D",
    "<DATE>": "08/11/20",
    "<TIME>": "00:00",
    "<CLOSE>": 3055.40666
  },
  {
    "<TICKER>": "VSAT US",
    "<PER>": "D",
    "<DATE>": "08/12/20",
    "<TIME>": "00:00",
    "<CLOSE>": 3080.94682
  },
  {
    "<TICKER>": "VSAT US",
    "<PER>": "D",
    "<DATE>": "08/13/20",
    "<TIME>": "00:00",
    "<CLOSE>": 2996.98468
  },
  {
    "<TICKER>": "VSAT US",
    "<PER>": "D",
    "<DATE>": "08/14/20",
    "<TIME>": "00:00",
    "<CLOSE>": 3014.98404
  },
  {
    "<TICKER>": "VSAT US",
    "<PER>": "D",
    "<DATE>": "08/17/20",
    "<TIME>": "00:00",
    "<CLOSE>": 3033.09174
  },
  {
    "<TICKER>": "VSAT US",
    "<PER>": "D",
    "<DATE>": "08/18/20",
    "<TIME>": "00:00",
    "<CLOSE>": 3019.85569
  },
  {
    "<TICKER>": "VSAT US",
    "<PER>": "D",
    "<DATE>": "08/19/20",
    "<TIME>": "00:00",
    "<CLOSE>": 2995.65759
  },
  {
    "<TICKER>": "VSAT US",
    "<PER>": "D",
    "<DATE>": "08/20/20",
    "<TIME>": "00:00",
    "<CLOSE>": 2982.63741
  },
  {
    "<TICKER>": "VSAT US",
    "<PER>": "D",
    "<DATE>": "08/21/20",
    "<TIME>": "00:00",
    "<CLOSE>": 2938.9133
  },
  {
    "<TICKER>": "VSAT US",
    "<PER>": "D",
    "<DATE>": "08/24/20",
    "<TIME>": "00:00",
    "<CLOSE>": 3025.269
  },
  {
    "<TICKER>": "VSAT US",
    "<PER>": "D",
    "<DATE>": "08/25/20",
    "<TIME>": "00:00",
    "<CLOSE>": 3028.12852
  },
  {
    "<TICKER>": "VSAT US",
    "<PER>": "D",
    "<DATE>": "08/26/20",
    "<TIME>": "00:00",
    "<CLOSE>": 3018.91612
  },
  {
    "<TICKER>": "VSAT US",
    "<PER>": "D",
    "<DATE>": "08/27/20",
    "<TIME>": "00:00",
    "<CLOSE>": 3013.89464
  },
  {
    "<TICKER>": "VSAT US",
    "<PER>": "D",
    "<DATE>": "08/28/20",
    "<TIME>": "00:00",
    "<CLOSE>": 2980.4476
  },
  {
    "<TICKER>": "VSAT US",
    "<PER>": "D",
    "<DATE>": "08/31/20",
    "<TIME>": "00:00",
    "<CLOSE>": 2954.46222
  },
  {
    "<TICKER>": "VSAT US",
    "<PER>": "D",
    "<DATE>": "09/01/20",
    "<TIME>": "00:00",
    "<CLOSE>": 2894.95983
  },
  {
    "<TICKER>": "VSAT US",
    "<PER>": "D",
    "<DATE>": "09/02/20",
    "<TIME>": "00:00",
    "<CLOSE>": 2948.48799
  },
  {
    "<TICKER>": "VSAT US",
    "<PER>": "D",
    "<DATE>": "09/03/20",
    "<TIME>": "00:00",
    "<CLOSE>": 2819.58318
  },
  {
    "<TICKER>": "VSAT US",
    "<PER>": "D",
    "<DATE>": "09/04/20",
    "<TIME>": "00:00",
    "<CLOSE>": 2804.13716
  },
  {
    "<TICKER>": "VSAT US",
    "<PER>": "D",
    "<DATE>": "09/07/20",
    "<TIME>": "00:00",
    "<CLOSE>": 2804.13716
  },
  {
    "<TICKER>": "VSAT US",
    "<PER>": "D",
    "<DATE>": "09/08/20",
    "<TIME>": "00:00",
    "<CLOSE>": 2886.50698
  },
  {
    "<TICKER>": "VSAT US",
    "<PER>": "D",
    "<DATE>": "09/09/20",
    "<TIME>": "00:00",
    "<CLOSE>": 2804.43026
  },
  {
    "<TICKER>": "VSAT US",
    "<PER>": "D",
    "<DATE>": "09/10/20",
    "<TIME>": "00:00",
    "<CLOSE>": 2651.96814
  },
  {
    "<TICKER>": "VSAT US",
    "<PER>": "D",
    "<DATE>": "09/11/20",
    "<TIME>": "00:00",
    "<CLOSE>": 2698.65355
  },
  {
    "<TICKER>": "VSAT US",
    "<PER>": "D",
    "<DATE>": "09/14/20",
    "<TIME>": "00:00",
    "<CLOSE>": 2740.48842
  },
  {
    "<TICKER>": "VSAT US",
    "<PER>": "D",
    "<DATE>": "09/15/20",
    "<TIME>": "00:00",
    "<CLOSE>": 2648.01901
  },
  {
    "<TICKER>": "VSAT US",
    "<PER>": "D",
    "<DATE>": "09/16/20",
    "<TIME>": "00:00",
    "<CLOSE>": 2661.76934
  },
  {
    "<TICKER>": "VSAT US",
    "<PER>": "D",
    "<DATE>": "09/17/20",
    "<TIME>": "00:00",
    "<CLOSE>": 2672.46712
  },
  {
    "<TICKER>": "VSAT US",
    "<PER>": "D",
    "<DATE>": "09/18/20",
    "<TIME>": "00:00",
    "<CLOSE>": 2652.22344
  },
  {
    "<TICKER>": "VSAT US",
    "<PER>": "D",
    "<DATE>": "09/21/20",
    "<TIME>": "00:00",
    "<CLOSE>": 2662.98336
  },
  {
    "<TICKER>": "VSAT US",
    "<PER>": "D",
    "<DATE>": "09/22/20",
    "<TIME>": "00:00",
    "<CLOSE>": 2630.76473
  },
  {
    "<TICKER>": "VSAT US",
    "<PER>": "D",
    "<DATE>": "09/23/20",
    "<TIME>": "00:00",
    "<CLOSE>": 2581.19384
  },
  {
    "<TICKER>": "VSAT US",
    "<PER>": "D",
    "<DATE>": "09/24/20",
    "<TIME>": "00:00",
    "<CLOSE>": 2512.59138
  },
  {
    "<TICKER>": "VSAT US",
    "<PER>": "D",
    "<DATE>": "09/25/20",
    "<TIME>": "00:00",
    "<CLOSE>": 2582.11719
  },
  {
    "<TICKER>": "VSAT US",
    "<PER>": "D",
    "<DATE>": "09/28/20",
    "<TIME>": "00:00",
    "<CLOSE>": 2707.25651
  },
  {
    "<TICKER>": "VSAT US",
    "<PER>": "D",
    "<DATE>": "09/29/20",
    "<TIME>": "00:00",
    "<CLOSE>": 2706.48026
  },
  {
    "<TICKER>": "VSAT US",
    "<PER>": "D",
    "<DATE>": "09/30/20",
    "<TIME>": "00:00",
    "<CLOSE>": 2669.66131
  },
  {
    "<TICKER>": "VSAT US",
    "<PER>": "D",
    "<DATE>": "10/01/20",
    "<TIME>": "00:00",
    "<CLOSE>": 2662.19713
  },
  {
    "<TICKER>": "VSAT US",
    "<PER>": "D",
    "<DATE>": "10/02/20",
    "<TIME>": "00:00",
    "<CLOSE>": 2694.85336
  },
  {
    "<TICKER>": "VSAT US",
    "<PER>": "D",
    "<DATE>": "10/05/20",
    "<TIME>": "00:00",
    "<CLOSE>": 2684.81599
  },
  {
    "<TICKER>": "VSAT US",
    "<PER>": "D",
    "<DATE>": "10/06/20",
    "<TIME>": "00:00",
    "<CLOSE>": 2660.76162
  },
  {
    "<TICKER>": "VSAT US",
    "<PER>": "D",
    "<DATE>": "10/07/20",
    "<TIME>": "00:00",
    "<CLOSE>": 2668.48818
  },
  {
    "<TICKER>": "VSAT US",
    "<PER>": "D",
    "<DATE>": "10/08/20",
    "<TIME>": "00:00",
    "<CLOSE>": 2719.09503
  },
  {
    "<TICKER>": "VSAT US",
    "<PER>": "D",
    "<DATE>": "10/09/20",
    "<TIME>": "00:00",
    "<CLOSE>": 2737.37919
  },
  {
    "<TICKER>": "VSAT US",
    "<PER>": "D",
    "<DATE>": "10/12/20",
    "<TIME>": "00:00",
    "<CLOSE>": 2787.87871
  },
  {
    "<TICKER>": "VSAT US",
    "<PER>": "D",
    "<DATE>": "10/13/20",
    "<TIME>": "00:00",
    "<CLOSE>": 2686.29366
  },
  {
    "<TICKER>": "VSAT US",
    "<PER>": "D",
    "<DATE>": "10/14/20",
    "<TIME>": "00:00",
    "<CLOSE>": 2658.24979
  },
  {
    "<TICKER>": "VSAT US",
    "<PER>": "D",
    "<DATE>": "10/15/20",
    "<TIME>": "00:00",
    "<CLOSE>": 2702.82625
  },
  {
    "<TICKER>": "VSAT US",
    "<PER>": "D",
    "<DATE>": "10/16/20",
    "<TIME>": "00:00",
    "<CLOSE>": 2704.95882
  },
  {
    "<TICKER>": "VSAT US",
    "<PER>": "D",
    "<DATE>": "10/19/20",
    "<TIME>": "00:00",
    "<CLOSE>": 2660.72646
  },
  {
    "<TICKER>": "VSAT US",
    "<PER>": "D",
    "<DATE>": "10/20/20",
    "<TIME>": "00:00",
    "<CLOSE>": 2706.79088
  },
  {
    "<TICKER>": "VSAT US",
    "<PER>": "D",
    "<DATE>": "10/21/20",
    "<TIME>": "00:00",
    "<CLOSE>": 2670.57952
  },
  {
    "<TICKER>": "VSAT US",
    "<PER>": "D",
    "<DATE>": "10/22/20",
    "<TIME>": "00:00",
    "<CLOSE>": 2690.42779
  },
  {
    "<TICKER>": "VSAT US",
    "<PER>": "D",
    "<DATE>": "10/23/20",
    "<TIME>": "00:00",
    "<CLOSE>": 2728.0342
  },
  {
    "<TICKER>": "VSAT US",
    "<PER>": "D",
    "<DATE>": "10/26/20",
    "<TIME>": "00:00",
    "<CLOSE>": 2652.7443
  },
  {
    "<TICKER>": "VSAT US",
    "<PER>": "D",
    "<DATE>": "10/27/20",
    "<TIME>": "00:00",
    "<CLOSE>": 2651.87578
  },
  {
    "<TICKER>": "VSAT US",
    "<PER>": "D",
    "<DATE>": "10/28/20",
    "<TIME>": "00:00",
    "<CLOSE>": 2652.78352
  },
  {
    "<TICKER>": "VSAT US",
    "<PER>": "D",
    "<DATE>": "10/29/20",
    "<TIME>": "00:00",
    "<CLOSE>": 2672.2787
  },
  {
    "<TICKER>": "VSAT US",
    "<PER>": "D",
    "<DATE>": "10/30/20",
    "<TIME>": "00:00",
    "<CLOSE>": 2693.70078
  },
  {
    "<TICKER>": "VSAT US",
    "<PER>": "D",
    "<DATE>": "11/02/20",
    "<TIME>": "00:00",
    "<CLOSE>": 2794.59763
  },
  {
    "<TICKER>": "VSAT US",
    "<PER>": "D",
    "<DATE>": "11/03/20",
    "<TIME>": "00:00",
    "<CLOSE>": 2766.63667
  },
  {
    "<TICKER>": "VSAT US",
    "<PER>": "D",
    "<DATE>": "11/04/20",
    "<TIME>": "00:00",
    "<CLOSE>": 2503.52253
  },
  {
    "<TICKER>": "VSAT US",
    "<PER>": "D",
    "<DATE>": "11/05/20",
    "<TIME>": "00:00",
    "<CLOSE>": 2586.46648
  },
  {
    "<TICKER>": "VSAT US",
    "<PER>": "D",
    "<DATE>": "11/06/20",
    "<TIME>": "00:00",
    "<CLOSE>": 2570.79614
  },
  {
    "<TICKER>": "VSAT US",
    "<PER>": "D",
    "<DATE>": "11/09/20",
    "<TIME>": "00:00",
    "<CLOSE>": 2767.27968
  },
  {
    "<TICKER>": "VSAT US",
    "<PER>": "D",
    "<DATE>": "11/10/20",
    "<TIME>": "00:00",
    "<CLOSE>": 2644.31677
  },
  {
    "<TICKER>": "VSAT US",
    "<PER>": "D",
    "<DATE>": "11/11/20",
    "<TIME>": "00:00",
    "<CLOSE>": 2637.97934
  },
  {
    "<TICKER>": "VSAT US",
    "<PER>": "D",
    "<DATE>": "11/12/20",
    "<TIME>": "00:00",
    "<CLOSE>": 2575.392
  },
  {
    "<TICKER>": "VSAT US",
    "<PER>": "D",
    "<DATE>": "11/13/20",
    "<TIME>": "00:00",
    "<CLOSE>": 2680.1093
  },
  {
    "<TICKER>": "VSAT US",
    "<PER>": "D",
    "<DATE>": "11/16/20",
    "<TIME>": "00:00",
    "<CLOSE>": 2798.11755
  },
  {
    "<TICKER>": "VSAT US",
    "<PER>": "D",
    "<DATE>": "11/17/20",
    "<TIME>": "00:00",
    "<CLOSE>": 2717.58798
  },
  {
    "<TICKER>": "VSAT US",
    "<PER>": "D",
    "<DATE>": "11/18/20",
    "<TIME>": "00:00",
    "<CLOSE>": 2745.70087
  },
  {
    "<TICKER>": "VSAT US",
    "<PER>": "D",
    "<DATE>": "11/19/20",
    "<TIME>": "00:00",
    "<CLOSE>": 2670.41581
  },
  {
    "<TICKER>": "VSAT US",
    "<PER>": "D",
    "<DATE>": "11/20/20",
    "<TIME>": "00:00",
    "<CLOSE>": 2649.41645
  },
  {
    "<TICKER>": "VSAT US",
    "<PER>": "D",
    "<DATE>": "11/23/20",
    "<TIME>": "00:00",
    "<CLOSE>": 2718.7077
  },
  {
    "<TICKER>": "VSAT US",
    "<PER>": "D",
    "<DATE>": "11/24/20",
    "<TIME>": "00:00",
    "<CLOSE>": 2768.95853
  },
  {
    "<TICKER>": "VSAT US",
    "<PER>": "D",
    "<DATE>": "11/25/20",
    "<TIME>": "00:00",
    "<CLOSE>": 2710.17396
  },
  {
    "<TICKER>": "VSAT US",
    "<PER>": "D",
    "<DATE>": "11/26/20",
    "<TIME>": "00:00",
    "<CLOSE>": 2710.17396
  },
  {
    "<TICKER>": "VSAT US",
    "<PER>": "D",
    "<DATE>": "11/27/20",
    "<TIME>": "00:00",
    "<CLOSE>": 2701.02223
  },
  {
    "<TICKER>": "VSAT US",
    "<PER>": "D",
    "<DATE>": "11/30/20",
    "<TIME>": "00:00",
    "<CLOSE>": 2598.7254
  },
  {
    "<TICKER>": "VSAT US",
    "<PER>": "D",
    "<DATE>": "12/01/20",
    "<TIME>": "00:00",
    "<CLOSE>": 2638.89147
  },
  {
    "<TICKER>": "VSAT US",
    "<PER>": "D",
    "<DATE>": "12/02/20",
    "<TIME>": "00:00",
    "<CLOSE>": 2577.27456
  },
  {
    "<TICKER>": "VSAT US",
    "<PER>": "D",
    "<DATE>": "12/03/20",
    "<TIME>": "00:00",
    "<CLOSE>": 2596.61547
  },
  {
    "<TICKER>": "VSAT US",
    "<PER>": "D",
    "<DATE>": "12/04/20",
    "<TIME>": "00:00",
    "<CLOSE>": 2609.22262
  },
  {
    "<TICKER>": "VSAT US",
    "<PER>": "D",
    "<DATE>": "12/07/20",
    "<TIME>": "00:00",
    "<CLOSE>": 2584.8592
  },
  {
    "<TICKER>": "VSAT US",
    "<PER>": "D",
    "<DATE>": "12/08/20",
    "<TIME>": "00:00",
    "<CLOSE>": 2509.76756
  },
  {
    "<TICKER>": "VSAT US",
    "<PER>": "D",
    "<DATE>": "12/09/20",
    "<TIME>": "00:00",
    "<CLOSE>": 2577.82219
  },
  {
    "<TICKER>": "VSAT US",
    "<PER>": "D",
    "<DATE>": "12/10/20",
    "<TIME>": "00:00",
    "<CLOSE>": 2514.65634
  },
  {
    "<TICKER>": "VSAT US",
    "<PER>": "D",
    "<DATE>": "12/11/20",
    "<TIME>": "00:00",
    "<CLOSE>": 2547.71622
  },
  {
    "<TICKER>": "VSAT US",
    "<PER>": "D",
    "<DATE>": "12/14/20",
    "<TIME>": "00:00",
    "<CLOSE>": 2547.55935
  },
  {
    "<TICKER>": "VSAT US",
    "<PER>": "D",
    "<DATE>": "12/15/20",
    "<TIME>": "00:00",
    "<CLOSE>": 2459.19167
  },
  {
    "<TICKER>": "VSAT US",
    "<PER>": "D",
    "<DATE>": "12/16/20",
    "<TIME>": "00:00",
    "<CLOSE>": 2413.61309
  },
  {
    "<TICKER>": "VSAT US",
    "<PER>": "D",
    "<DATE>": "12/17/20",
    "<TIME>": "00:00",
    "<CLOSE>": 2335.68396
  },
  {
    "<TICKER>": "VSAT US",
    "<PER>": "D",
    "<DATE>": "12/18/20",
    "<TIME>": "00:00",
    "<CLOSE>": 2308.52821
  },
  {
    "<TICKER>": "VSAT US",
    "<PER>": "D",
    "<DATE>": "12/21/20",
    "<TIME>": "00:00",
    "<CLOSE>": 2285.24506
  },
  {
    "<TICKER>": "VSAT US",
    "<PER>": "D",
    "<DATE>": "12/22/20",
    "<TIME>": "00:00",
    "<CLOSE>": 2424.28984
  },
  {
    "<TICKER>": "VSAT US",
    "<PER>": "D",
    "<DATE>": "12/23/20",
    "<TIME>": "00:00",
    "<CLOSE>": 2509.19551
  },
  {
    "<TICKER>": "VSAT US",
    "<PER>": "D",
    "<DATE>": "12/24/20",
    "<TIME>": "00:00",
    "<CLOSE>": 2474.99339
  },
  {
    "<TICKER>": "VSAT US",
    "<PER>": "D",
    "<DATE>": "12/25/20",
    "<TIME>": "00:00",
    "<CLOSE>": 2474.99339
  },
  {
    "<TICKER>": "VSAT US",
    "<PER>": "D",
    "<DATE>": "12/28/20",
    "<TIME>": "00:00",
    "<CLOSE>": 2546.14959
  },
  {
    "<TICKER>": "VSAT US",
    "<PER>": "D",
    "<DATE>": "12/29/20",
    "<TIME>": "00:00",
    "<CLOSE>": 2483.65295
  },
  {
    "<TICKER>": "VSAT US",
    "<PER>": "D",
    "<DATE>": "12/30/20",
    "<TIME>": "00:00",
    "<CLOSE>": 2475.60423
  },
  {
    "<TICKER>": "VSAT US",
    "<PER>": "D",
    "<DATE>": "12/31/20",
    "<TIME>": "00:00",
    "<CLOSE>": 2422.33941
  }
]