[
  {
    "<TICKER>": "TWTR US",
    "<PER>": "D",
    "<DATE>": "2/1/19",
    "<TIME>": "00:00",
    "<CLOSE>": 33.19
  },
  {
    "<TICKER>": "TWTR US",
    "<PER>": "D",
    "<DATE>": "2/2/19",
    "<TIME>": "00:00",
    "<CLOSE>": 33.19
  },
  {
    "<TICKER>": "TWTR US",
    "<PER>": "D",
    "<DATE>": "2/3/19",
    "<TIME>": "00:00",
    "<CLOSE>": 33.19
  },
  {
    "<TICKER>": "TWTR US",
    "<PER>": "D",
    "<DATE>": "2/4/19",
    "<TIME>": "00:00",
    "<CLOSE>": 33.94
  },
  {
    "<TICKER>": "TWTR US",
    "<PER>": "D",
    "<DATE>": "2/5/19",
    "<TIME>": "00:00",
    "<CLOSE>": 34.37
  },
  {
    "<TICKER>": "TWTR US",
    "<PER>": "D",
    "<DATE>": "2/6/19",
    "<TIME>": "00:00",
    "<CLOSE>": 34.16
  },
  {
    "<TICKER>": "TWTR US",
    "<PER>": "D",
    "<DATE>": "2/7/19",
    "<TIME>": "00:00",
    "<CLOSE>": 30.8
  },
  {
    "<TICKER>": "TWTR US",
    "<PER>": "D",
    "<DATE>": "2/8/19",
    "<TIME>": "00:00",
    "<CLOSE>": 30.01
  },
  {
    "<TICKER>": "TWTR US",
    "<PER>": "D",
    "<DATE>": "2/9/19",
    "<TIME>": "00:00",
    "<CLOSE>": 30.01
  },
  {
    "<TICKER>": "TWTR US",
    "<PER>": "D",
    "<DATE>": "2/10/19",
    "<TIME>": "00:00",
    "<CLOSE>": 30.01
  },
  {
    "<TICKER>": "TWTR US",
    "<PER>": "D",
    "<DATE>": "2/11/19",
    "<TIME>": "00:00",
    "<CLOSE>": 30.23
  },
  {
    "<TICKER>": "TWTR US",
    "<PER>": "D",
    "<DATE>": "2/12/19",
    "<TIME>": "00:00",
    "<CLOSE>": 30.39
  },
  {
    "<TICKER>": "TWTR US",
    "<PER>": "D",
    "<DATE>": "2/13/19",
    "<TIME>": "00:00",
    "<CLOSE>": 31.12
  },
  {
    "<TICKER>": "TWTR US",
    "<PER>": "D",
    "<DATE>": "2/14/19",
    "<TIME>": "00:00",
    "<CLOSE>": 30.96
  },
  {
    "<TICKER>": "TWTR US",
    "<PER>": "D",
    "<DATE>": "2/15/19",
    "<TIME>": "00:00",
    "<CLOSE>": 31.23
  },
  {
    "<TICKER>": "TWTR US",
    "<PER>": "D",
    "<DATE>": "2/16/19",
    "<TIME>": "00:00",
    "<CLOSE>": 31.23
  },
  {
    "<TICKER>": "TWTR US",
    "<PER>": "D",
    "<DATE>": "2/17/19",
    "<TIME>": "00:00",
    "<CLOSE>": 31.23
  },
  {
    "<TICKER>": "TWTR US",
    "<PER>": "D",
    "<DATE>": "2/18/19",
    "<TIME>": "00:00",
    "<CLOSE>": 31.23
  },
  {
    "<TICKER>": "TWTR US",
    "<PER>": "D",
    "<DATE>": "2/19/19",
    "<TIME>": "00:00",
    "<CLOSE>": 31.65
  },
  {
    "<TICKER>": "TWTR US",
    "<PER>": "D",
    "<DATE>": "2/20/19",
    "<TIME>": "00:00",
    "<CLOSE>": 31.37
  },
  {
    "<TICKER>": "TWTR US",
    "<PER>": "D",
    "<DATE>": "2/21/19",
    "<TIME>": "00:00",
    "<CLOSE>": 30.76
  },
  {
    "<TICKER>": "TWTR US",
    "<PER>": "D",
    "<DATE>": "2/22/19",
    "<TIME>": "00:00",
    "<CLOSE>": 31.71
  },
  {
    "<TICKER>": "TWTR US",
    "<PER>": "D",
    "<DATE>": "2/23/19",
    "<TIME>": "00:00",
    "<CLOSE>": 31.71
  },
  {
    "<TICKER>": "TWTR US",
    "<PER>": "D",
    "<DATE>": "2/24/19",
    "<TIME>": "00:00",
    "<CLOSE>": 31.71
  },
  {
    "<TICKER>": "TWTR US",
    "<PER>": "D",
    "<DATE>": "2/25/19",
    "<TIME>": "00:00",
    "<CLOSE>": 31.99
  },
  {
    "<TICKER>": "TWTR US",
    "<PER>": "D",
    "<DATE>": "2/26/19",
    "<TIME>": "00:00",
    "<CLOSE>": 31.01
  },
  {
    "<TICKER>": "TWTR US",
    "<PER>": "D",
    "<DATE>": "2/27/19",
    "<TIME>": "00:00",
    "<CLOSE>": 30.41
  },
  {
    "<TICKER>": "TWTR US",
    "<PER>": "D",
    "<DATE>": "2/28/19",
    "<TIME>": "00:00",
    "<CLOSE>": 30.78
  },
  {
    "<TICKER>": "TWTR US",
    "<PER>": "D",
    "<DATE>": "3/1/19",
    "<TIME>": "00:00",
    "<CLOSE>": 30.62
  },
  {
    "<TICKER>": "TWTR US",
    "<PER>": "D",
    "<DATE>": "3/2/19",
    "<TIME>": "00:00",
    "<CLOSE>": 30.62
  },
  {
    "<TICKER>": "TWTR US",
    "<PER>": "D",
    "<DATE>": "3/3/19",
    "<TIME>": "00:00",
    "<CLOSE>": 30.62
  },
  {
    "<TICKER>": "TWTR US",
    "<PER>": "D",
    "<DATE>": "3/4/19",
    "<TIME>": "00:00",
    "<CLOSE>": 30.5
  },
  {
    "<TICKER>": "TWTR US",
    "<PER>": "D",
    "<DATE>": "3/5/19",
    "<TIME>": "00:00",
    "<CLOSE>": 31.03
  },
  {
    "<TICKER>": "TWTR US",
    "<PER>": "D",
    "<DATE>": "3/6/19",
    "<TIME>": "00:00",
    "<CLOSE>": 30.8
  },
  {
    "<TICKER>": "TWTR US",
    "<PER>": "D",
    "<DATE>": "3/7/19",
    "<TIME>": "00:00",
    "<CLOSE>": 30.12
  },
  {
    "<TICKER>": "TWTR US",
    "<PER>": "D",
    "<DATE>": "3/8/19",
    "<TIME>": "00:00",
    "<CLOSE>": 30.04
  },
  {
    "<TICKER>": "TWTR US",
    "<PER>": "D",
    "<DATE>": "3/9/19",
    "<TIME>": "00:00",
    "<CLOSE>": 30.04
  },
  {
    "<TICKER>": "TWTR US",
    "<PER>": "D",
    "<DATE>": "3/10/19",
    "<TIME>": "00:00",
    "<CLOSE>": 30.04
  },
  {
    "<TICKER>": "TWTR US",
    "<PER>": "D",
    "<DATE>": "3/11/19",
    "<TIME>": "00:00",
    "<CLOSE>": 30.87
  },
  {
    "<TICKER>": "TWTR US",
    "<PER>": "D",
    "<DATE>": "3/12/19",
    "<TIME>": "00:00",
    "<CLOSE>": 31.16
  },
  {
    "<TICKER>": "TWTR US",
    "<PER>": "D",
    "<DATE>": "3/13/19",
    "<TIME>": "00:00",
    "<CLOSE>": 31.3
  },
  {
    "<TICKER>": "TWTR US",
    "<PER>": "D",
    "<DATE>": "3/14/19",
    "<TIME>": "00:00",
    "<CLOSE>": 31.03
  },
  {
    "<TICKER>": "TWTR US",
    "<PER>": "D",
    "<DATE>": "3/15/19",
    "<TIME>": "00:00",
    "<CLOSE>": 31.22
  },
  {
    "<TICKER>": "TWTR US",
    "<PER>": "D",
    "<DATE>": "3/16/19",
    "<TIME>": "00:00",
    "<CLOSE>": 31.22
  },
  {
    "<TICKER>": "TWTR US",
    "<PER>": "D",
    "<DATE>": "3/17/19",
    "<TIME>": "00:00",
    "<CLOSE>": 31.22
  },
  {
    "<TICKER>": "TWTR US",
    "<PER>": "D",
    "<DATE>": "3/18/19",
    "<TIME>": "00:00",
    "<CLOSE>": 31.08
  },
  {
    "<TICKER>": "TWTR US",
    "<PER>": "D",
    "<DATE>": "3/19/19",
    "<TIME>": "00:00",
    "<CLOSE>": 31.27
  },
  {
    "<TICKER>": "TWTR US",
    "<PER>": "D",
    "<DATE>": "3/20/19",
    "<TIME>": "00:00",
    "<CLOSE>": 32.57
  },
  {
    "<TICKER>": "TWTR US",
    "<PER>": "D",
    "<DATE>": "3/21/19",
    "<TIME>": "00:00",
    "<CLOSE>": 32.61
  },
  {
    "<TICKER>": "TWTR US",
    "<PER>": "D",
    "<DATE>": "3/22/19",
    "<TIME>": "00:00",
    "<CLOSE>": 33.02
  },
  {
    "<TICKER>": "TWTR US",
    "<PER>": "D",
    "<DATE>": "3/23/19",
    "<TIME>": "00:00",
    "<CLOSE>": 33.02
  },
  {
    "<TICKER>": "TWTR US",
    "<PER>": "D",
    "<DATE>": "3/24/19",
    "<TIME>": "00:00",
    "<CLOSE>": 33.02
  },
  {
    "<TICKER>": "TWTR US",
    "<PER>": "D",
    "<DATE>": "3/25/19",
    "<TIME>": "00:00",
    "<CLOSE>": 32.59
  },
  {
    "<TICKER>": "TWTR US",
    "<PER>": "D",
    "<DATE>": "3/26/19",
    "<TIME>": "00:00",
    "<CLOSE>": 33.06
  },
  {
    "<TICKER>": "TWTR US",
    "<PER>": "D",
    "<DATE>": "3/27/19",
    "<TIME>": "00:00",
    "<CLOSE>": 32.28
  },
  {
    "<TICKER>": "TWTR US",
    "<PER>": "D",
    "<DATE>": "3/28/19",
    "<TIME>": "00:00",
    "<CLOSE>": 32.87
  },
  {
    "<TICKER>": "TWTR US",
    "<PER>": "D",
    "<DATE>": "3/29/19",
    "<TIME>": "00:00",
    "<CLOSE>": 32.88
  },
  {
    "<TICKER>": "TWTR US",
    "<PER>": "D",
    "<DATE>": "3/30/19",
    "<TIME>": "00:00",
    "<CLOSE>": 32.88
  },
  {
    "<TICKER>": "TWTR US",
    "<PER>": "D",
    "<DATE>": "3/31/19",
    "<TIME>": "00:00",
    "<CLOSE>": 32.88
  },
  {
    "<TICKER>": "TWTR US",
    "<PER>": "D",
    "<DATE>": "4/1/19",
    "<TIME>": "00:00",
    "<CLOSE>": 33.44
  },
  {
    "<TICKER>": "TWTR US",
    "<PER>": "D",
    "<DATE>": "4/2/19",
    "<TIME>": "00:00",
    "<CLOSE>": 33.75
  },
  {
    "<TICKER>": "TWTR US",
    "<PER>": "D",
    "<DATE>": "4/3/19",
    "<TIME>": "00:00",
    "<CLOSE>": 34.38
  },
  {
    "<TICKER>": "TWTR US",
    "<PER>": "D",
    "<DATE>": "4/4/19",
    "<TIME>": "00:00",
    "<CLOSE>": 34.42
  },
  {
    "<TICKER>": "TWTR US",
    "<PER>": "D",
    "<DATE>": "4/5/19",
    "<TIME>": "00:00",
    "<CLOSE>": 34.72
  },
  {
    "<TICKER>": "TWTR US",
    "<PER>": "D",
    "<DATE>": "4/6/19",
    "<TIME>": "00:00",
    "<CLOSE>": 34.72
  },
  {
    "<TICKER>": "TWTR US",
    "<PER>": "D",
    "<DATE>": "4/7/19",
    "<TIME>": "00:00",
    "<CLOSE>": 34.72
  },
  {
    "<TICKER>": "TWTR US",
    "<PER>": "D",
    "<DATE>": "4/8/19",
    "<TIME>": "00:00",
    "<CLOSE>": 34.86
  },
  {
    "<TICKER>": "TWTR US",
    "<PER>": "D",
    "<DATE>": "4/9/19",
    "<TIME>": "00:00",
    "<CLOSE>": 35.14
  },
  {
    "<TICKER>": "TWTR US",
    "<PER>": "D",
    "<DATE>": "4/10/19",
    "<TIME>": "00:00",
    "<CLOSE>": 34.75
  },
  {
    "<TICKER>": "TWTR US",
    "<PER>": "D",
    "<DATE>": "4/11/19",
    "<TIME>": "00:00",
    "<CLOSE>": 34.58
  },
  {
    "<TICKER>": "TWTR US",
    "<PER>": "D",
    "<DATE>": "4/12/19",
    "<TIME>": "00:00",
    "<CLOSE>": 34.37
  },
  {
    "<TICKER>": "TWTR US",
    "<PER>": "D",
    "<DATE>": "4/13/19",
    "<TIME>": "00:00",
    "<CLOSE>": 34.37
  },
  {
    "<TICKER>": "TWTR US",
    "<PER>": "D",
    "<DATE>": "4/14/19",
    "<TIME>": "00:00",
    "<CLOSE>": 34.37
  },
  {
    "<TICKER>": "TWTR US",
    "<PER>": "D",
    "<DATE>": "4/15/19",
    "<TIME>": "00:00",
    "<CLOSE>": 34.71
  },
  {
    "<TICKER>": "TWTR US",
    "<PER>": "D",
    "<DATE>": "4/16/19",
    "<TIME>": "00:00",
    "<CLOSE>": 34.46
  },
  {
    "<TICKER>": "TWTR US",
    "<PER>": "D",
    "<DATE>": "4/17/19",
    "<TIME>": "00:00",
    "<CLOSE>": 34.48
  },
  {
    "<TICKER>": "TWTR US",
    "<PER>": "D",
    "<DATE>": "4/18/19",
    "<TIME>": "00:00",
    "<CLOSE>": 34.4
  },
  {
    "<TICKER>": "TWTR US",
    "<PER>": "D",
    "<DATE>": "4/19/19",
    "<TIME>": "00:00",
    "<CLOSE>": 34.4
  },
  {
    "<TICKER>": "TWTR US",
    "<PER>": "D",
    "<DATE>": "4/20/19",
    "<TIME>": "00:00",
    "<CLOSE>": 34.4
  },
  {
    "<TICKER>": "TWTR US",
    "<PER>": "D",
    "<DATE>": "4/21/19",
    "<TIME>": "00:00",
    "<CLOSE>": 34.4
  },
  {
    "<TICKER>": "TWTR US",
    "<PER>": "D",
    "<DATE>": "4/22/19",
    "<TIME>": "00:00",
    "<CLOSE>": 34.39
  },
  {
    "<TICKER>": "TWTR US",
    "<PER>": "D",
    "<DATE>": "4/23/19",
    "<TIME>": "00:00",
    "<CLOSE>": 39.77
  },
  {
    "<TICKER>": "TWTR US",
    "<PER>": "D",
    "<DATE>": "4/24/19",
    "<TIME>": "00:00",
    "<CLOSE>": 39.29
  },
  {
    "<TICKER>": "TWTR US",
    "<PER>": "D",
    "<DATE>": "4/25/19",
    "<TIME>": "00:00",
    "<CLOSE>": 38.48
  },
  {
    "<TICKER>": "TWTR US",
    "<PER>": "D",
    "<DATE>": "4/26/19",
    "<TIME>": "00:00",
    "<CLOSE>": 38.67
  },
  {
    "<TICKER>": "TWTR US",
    "<PER>": "D",
    "<DATE>": "4/27/19",
    "<TIME>": "00:00",
    "<CLOSE>": 38.67
  },
  {
    "<TICKER>": "TWTR US",
    "<PER>": "D",
    "<DATE>": "4/28/19",
    "<TIME>": "00:00",
    "<CLOSE>": 38.67
  },
  {
    "<TICKER>": "TWTR US",
    "<PER>": "D",
    "<DATE>": "4/29/19",
    "<TIME>": "00:00",
    "<CLOSE>": 39.78
  },
  {
    "<TICKER>": "TWTR US",
    "<PER>": "D",
    "<DATE>": "4/30/19",
    "<TIME>": "00:00",
    "<CLOSE>": 39.91
  },
  {
    "<TICKER>": "TWTR US",
    "<PER>": "D",
    "<DATE>": "5/1/19",
    "<TIME>": "00:00",
    "<CLOSE>": 39.29
  },
  {
    "<TICKER>": "TWTR US",
    "<PER>": "D",
    "<DATE>": "5/2/19",
    "<TIME>": "00:00",
    "<CLOSE>": 39.95
  },
  {
    "<TICKER>": "TWTR US",
    "<PER>": "D",
    "<DATE>": "5/3/19",
    "<TIME>": "00:00",
    "<CLOSE>": 40.8
  },
  {
    "<TICKER>": "TWTR US",
    "<PER>": "D",
    "<DATE>": "5/4/19",
    "<TIME>": "00:00",
    "<CLOSE>": 40.8
  },
  {
    "<TICKER>": "TWTR US",
    "<PER>": "D",
    "<DATE>": "5/5/19",
    "<TIME>": "00:00",
    "<CLOSE>": 40.8
  },
  {
    "<TICKER>": "TWTR US",
    "<PER>": "D",
    "<DATE>": "5/6/19",
    "<TIME>": "00:00",
    "<CLOSE>": 40.23
  },
  {
    "<TICKER>": "TWTR US",
    "<PER>": "D",
    "<DATE>": "5/7/19",
    "<TIME>": "00:00",
    "<CLOSE>": 38.62
  },
  {
    "<TICKER>": "TWTR US",
    "<PER>": "D",
    "<DATE>": "5/8/19",
    "<TIME>": "00:00",
    "<CLOSE>": 38.58
  },
  {
    "<TICKER>": "TWTR US",
    "<PER>": "D",
    "<DATE>": "5/9/19",
    "<TIME>": "00:00",
    "<CLOSE>": 38.79
  },
  {
    "<TICKER>": "TWTR US",
    "<PER>": "D",
    "<DATE>": "5/10/19",
    "<TIME>": "00:00",
    "<CLOSE>": 38.45
  },
  {
    "<TICKER>": "TWTR US",
    "<PER>": "D",
    "<DATE>": "5/11/19",
    "<TIME>": "00:00",
    "<CLOSE>": 38.45
  },
  {
    "<TICKER>": "TWTR US",
    "<PER>": "D",
    "<DATE>": "5/12/19",
    "<TIME>": "00:00",
    "<CLOSE>": 38.45
  },
  {
    "<TICKER>": "TWTR US",
    "<PER>": "D",
    "<DATE>": "5/13/19",
    "<TIME>": "00:00",
    "<CLOSE>": 36.59
  },
  {
    "<TICKER>": "TWTR US",
    "<PER>": "D",
    "<DATE>": "5/14/19",
    "<TIME>": "00:00",
    "<CLOSE>": 36.93
  },
  {
    "<TICKER>": "TWTR US",
    "<PER>": "D",
    "<DATE>": "5/15/19",
    "<TIME>": "00:00",
    "<CLOSE>": 37.9
  },
  {
    "<TICKER>": "TWTR US",
    "<PER>": "D",
    "<DATE>": "5/16/19",
    "<TIME>": "00:00",
    "<CLOSE>": 38.3
  },
  {
    "<TICKER>": "TWTR US",
    "<PER>": "D",
    "<DATE>": "5/17/19",
    "<TIME>": "00:00",
    "<CLOSE>": 37.5
  },
  {
    "<TICKER>": "TWTR US",
    "<PER>": "D",
    "<DATE>": "5/18/19",
    "<TIME>": "00:00",
    "<CLOSE>": 37.5
  },
  {
    "<TICKER>": "TWTR US",
    "<PER>": "D",
    "<DATE>": "5/19/19",
    "<TIME>": "00:00",
    "<CLOSE>": 37.5
  },
  {
    "<TICKER>": "TWTR US",
    "<PER>": "D",
    "<DATE>": "5/20/19",
    "<TIME>": "00:00",
    "<CLOSE>": 37.15
  },
  {
    "<TICKER>": "TWTR US",
    "<PER>": "D",
    "<DATE>": "5/21/19",
    "<TIME>": "00:00",
    "<CLOSE>": 37.47
  },
  {
    "<TICKER>": "TWTR US",
    "<PER>": "D",
    "<DATE>": "5/22/19",
    "<TIME>": "00:00",
    "<CLOSE>": 38.58
  },
  {
    "<TICKER>": "TWTR US",
    "<PER>": "D",
    "<DATE>": "5/23/19",
    "<TIME>": "00:00",
    "<CLOSE>": 37.19
  },
  {
    "<TICKER>": "TWTR US",
    "<PER>": "D",
    "<DATE>": "5/24/19",
    "<TIME>": "00:00",
    "<CLOSE>": 37.41
  },
  {
    "<TICKER>": "TWTR US",
    "<PER>": "D",
    "<DATE>": "5/25/19",
    "<TIME>": "00:00",
    "<CLOSE>": 37.41
  },
  {
    "<TICKER>": "TWTR US",
    "<PER>": "D",
    "<DATE>": "5/26/19",
    "<TIME>": "00:00",
    "<CLOSE>": 37.41
  },
  {
    "<TICKER>": "TWTR US",
    "<PER>": "D",
    "<DATE>": "5/27/19",
    "<TIME>": "00:00",
    "<CLOSE>": 37.41
  },
  {
    "<TICKER>": "TWTR US",
    "<PER>": "D",
    "<DATE>": "5/28/19",
    "<TIME>": "00:00",
    "<CLOSE>": 37.29
  },
  {
    "<TICKER>": "TWTR US",
    "<PER>": "D",
    "<DATE>": "5/29/19",
    "<TIME>": "00:00",
    "<CLOSE>": 36.85
  },
  {
    "<TICKER>": "TWTR US",
    "<PER>": "D",
    "<DATE>": "5/30/19",
    "<TIME>": "00:00",
    "<CLOSE>": 37.14
  },
  {
    "<TICKER>": "TWTR US",
    "<PER>": "D",
    "<DATE>": "5/31/19",
    "<TIME>": "00:00",
    "<CLOSE>": 36.44
  },
  {
    "<TICKER>": "TWTR US",
    "<PER>": "D",
    "<DATE>": "6/1/19",
    "<TIME>": "00:00",
    "<CLOSE>": 36.44
  },
  {
    "<TICKER>": "TWTR US",
    "<PER>": "D",
    "<DATE>": "6/2/19",
    "<TIME>": "00:00",
    "<CLOSE>": 36.44
  },
  {
    "<TICKER>": "TWTR US",
    "<PER>": "D",
    "<DATE>": "6/3/19",
    "<TIME>": "00:00",
    "<CLOSE>": 34.43
  },
  {
    "<TICKER>": "TWTR US",
    "<PER>": "D",
    "<DATE>": "6/4/19",
    "<TIME>": "00:00",
    "<CLOSE>": 36.1
  },
  {
    "<TICKER>": "TWTR US",
    "<PER>": "D",
    "<DATE>": "6/5/19",
    "<TIME>": "00:00",
    "<CLOSE>": 36.33
  },
  {
    "<TICKER>": "TWTR US",
    "<PER>": "D",
    "<DATE>": "6/6/19",
    "<TIME>": "00:00",
    "<CLOSE>": 36.59
  },
  {
    "<TICKER>": "TWTR US",
    "<PER>": "D",
    "<DATE>": "6/7/19",
    "<TIME>": "00:00",
    "<CLOSE>": 37.93
  },
  {
    "<TICKER>": "TWTR US",
    "<PER>": "D",
    "<DATE>": "6/8/19",
    "<TIME>": "00:00",
    "<CLOSE>": 37.93
  },
  {
    "<TICKER>": "TWTR US",
    "<PER>": "D",
    "<DATE>": "6/9/19",
    "<TIME>": "00:00",
    "<CLOSE>": 37.93
  },
  {
    "<TICKER>": "TWTR US",
    "<PER>": "D",
    "<DATE>": "6/10/19",
    "<TIME>": "00:00",
    "<CLOSE>": 37.64
  },
  {
    "<TICKER>": "TWTR US",
    "<PER>": "D",
    "<DATE>": "6/11/19",
    "<TIME>": "00:00",
    "<CLOSE>": 37.21
  },
  {
    "<TICKER>": "TWTR US",
    "<PER>": "D",
    "<DATE>": "6/12/19",
    "<TIME>": "00:00",
    "<CLOSE>": 37.49
  },
  {
    "<TICKER>": "TWTR US",
    "<PER>": "D",
    "<DATE>": "6/13/19",
    "<TIME>": "00:00",
    "<CLOSE>": 36.34
  },
  {
    "<TICKER>": "TWTR US",
    "<PER>": "D",
    "<DATE>": "6/14/19",
    "<TIME>": "00:00",
    "<CLOSE>": 36.15
  },
  {
    "<TICKER>": "TWTR US",
    "<PER>": "D",
    "<DATE>": "6/15/19",
    "<TIME>": "00:00",
    "<CLOSE>": 36.15
  },
  {
    "<TICKER>": "TWTR US",
    "<PER>": "D",
    "<DATE>": "6/16/19",
    "<TIME>": "00:00",
    "<CLOSE>": 36.15
  },
  {
    "<TICKER>": "TWTR US",
    "<PER>": "D",
    "<DATE>": "6/17/19",
    "<TIME>": "00:00",
    "<CLOSE>": 36.44
  },
  {
    "<TICKER>": "TWTR US",
    "<PER>": "D",
    "<DATE>": "6/18/19",
    "<TIME>": "00:00",
    "<CLOSE>": 36.65
  },
  {
    "<TICKER>": "TWTR US",
    "<PER>": "D",
    "<DATE>": "6/19/19",
    "<TIME>": "00:00",
    "<CLOSE>": 36.29
  },
  {
    "<TICKER>": "TWTR US",
    "<PER>": "D",
    "<DATE>": "6/20/19",
    "<TIME>": "00:00",
    "<CLOSE>": 35.44
  },
  {
    "<TICKER>": "TWTR US",
    "<PER>": "D",
    "<DATE>": "6/21/19",
    "<TIME>": "00:00",
    "<CLOSE>": 35.02
  },
  {
    "<TICKER>": "TWTR US",
    "<PER>": "D",
    "<DATE>": "6/22/19",
    "<TIME>": "00:00",
    "<CLOSE>": 35.02
  },
  {
    "<TICKER>": "TWTR US",
    "<PER>": "D",
    "<DATE>": "6/23/19",
    "<TIME>": "00:00",
    "<CLOSE>": 35.02
  },
  {
    "<TICKER>": "TWTR US",
    "<PER>": "D",
    "<DATE>": "6/24/19",
    "<TIME>": "00:00",
    "<CLOSE>": 35.58
  },
  {
    "<TICKER>": "TWTR US",
    "<PER>": "D",
    "<DATE>": "6/25/19",
    "<TIME>": "00:00",
    "<CLOSE>": 34.72
  },
  {
    "<TICKER>": "TWTR US",
    "<PER>": "D",
    "<DATE>": "6/26/19",
    "<TIME>": "00:00",
    "<CLOSE>": 35.22
  },
  {
    "<TICKER>": "TWTR US",
    "<PER>": "D",
    "<DATE>": "6/27/19",
    "<TIME>": "00:00",
    "<CLOSE>": 34.75
  },
  {
    "<TICKER>": "TWTR US",
    "<PER>": "D",
    "<DATE>": "6/28/19",
    "<TIME>": "00:00",
    "<CLOSE>": 34.9
  },
  {
    "<TICKER>": "TWTR US",
    "<PER>": "D",
    "<DATE>": "6/29/19",
    "<TIME>": "00:00",
    "<CLOSE>": 34.9
  },
  {
    "<TICKER>": "TWTR US",
    "<PER>": "D",
    "<DATE>": "6/30/19",
    "<TIME>": "00:00",
    "<CLOSE>": 34.9
  },
  {
    "<TICKER>": "TWTR US",
    "<PER>": "D",
    "<DATE>": "7/1/19",
    "<TIME>": "00:00",
    "<CLOSE>": 36.08
  },
  {
    "<TICKER>": "TWTR US",
    "<PER>": "D",
    "<DATE>": "7/2/19",
    "<TIME>": "00:00",
    "<CLOSE>": 36.22
  },
  {
    "<TICKER>": "TWTR US",
    "<PER>": "D",
    "<DATE>": "7/3/19",
    "<TIME>": "00:00",
    "<CLOSE>": 36.02
  },
  {
    "<TICKER>": "TWTR US",
    "<PER>": "D",
    "<DATE>": "7/4/19",
    "<TIME>": "00:00",
    "<CLOSE>": 36.02
  },
  {
    "<TICKER>": "TWTR US",
    "<PER>": "D",
    "<DATE>": "7/5/19",
    "<TIME>": "00:00",
    "<CLOSE>": 36.25
  },
  {
    "<TICKER>": "TWTR US",
    "<PER>": "D",
    "<DATE>": "7/6/19",
    "<TIME>": "00:00",
    "<CLOSE>": 36.25
  },
  {
    "<TICKER>": "TWTR US",
    "<PER>": "D",
    "<DATE>": "7/7/19",
    "<TIME>": "00:00",
    "<CLOSE>": 36.25
  },
  {
    "<TICKER>": "TWTR US",
    "<PER>": "D",
    "<DATE>": "7/8/19",
    "<TIME>": "00:00",
    "<CLOSE>": 36.45
  },
  {
    "<TICKER>": "TWTR US",
    "<PER>": "D",
    "<DATE>": "7/9/19",
    "<TIME>": "00:00",
    "<CLOSE>": 37.65
  },
  {
    "<TICKER>": "TWTR US",
    "<PER>": "D",
    "<DATE>": "7/10/19",
    "<TIME>": "00:00",
    "<CLOSE>": 37.47
  },
  {
    "<TICKER>": "TWTR US",
    "<PER>": "D",
    "<DATE>": "7/11/19",
    "<TIME>": "00:00",
    "<CLOSE>": 37.21
  },
  {
    "<TICKER>": "TWTR US",
    "<PER>": "D",
    "<DATE>": "7/12/19",
    "<TIME>": "00:00",
    "<CLOSE>": 37.84
  },
  {
    "<TICKER>": "TWTR US",
    "<PER>": "D",
    "<DATE>": "7/13/19",
    "<TIME>": "00:00",
    "<CLOSE>": 37.84
  },
  {
    "<TICKER>": "TWTR US",
    "<PER>": "D",
    "<DATE>": "7/14/19",
    "<TIME>": "00:00",
    "<CLOSE>": 37.84
  },
  {
    "<TICKER>": "TWTR US",
    "<PER>": "D",
    "<DATE>": "7/15/19",
    "<TIME>": "00:00",
    "<CLOSE>": 38.68
  },
  {
    "<TICKER>": "TWTR US",
    "<PER>": "D",
    "<DATE>": "7/16/19",
    "<TIME>": "00:00",
    "<CLOSE>": 37.99
  },
  {
    "<TICKER>": "TWTR US",
    "<PER>": "D",
    "<DATE>": "7/17/19",
    "<TIME>": "00:00",
    "<CLOSE>": 37.7
  },
  {
    "<TICKER>": "TWTR US",
    "<PER>": "D",
    "<DATE>": "7/18/19",
    "<TIME>": "00:00",
    "<CLOSE>": 37.66
  },
  {
    "<TICKER>": "TWTR US",
    "<PER>": "D",
    "<DATE>": "7/19/19",
    "<TIME>": "00:00",
    "<CLOSE>": 36.77
  },
  {
    "<TICKER>": "TWTR US",
    "<PER>": "D",
    "<DATE>": "7/20/19",
    "<TIME>": "00:00",
    "<CLOSE>": 36.77
  },
  {
    "<TICKER>": "TWTR US",
    "<PER>": "D",
    "<DATE>": "7/21/19",
    "<TIME>": "00:00",
    "<CLOSE>": 36.77
  },
  {
    "<TICKER>": "TWTR US",
    "<PER>": "D",
    "<DATE>": "7/22/19",
    "<TIME>": "00:00",
    "<CLOSE>": 37.58
  },
  {
    "<TICKER>": "TWTR US",
    "<PER>": "D",
    "<DATE>": "7/23/19",
    "<TIME>": "00:00",
    "<CLOSE>": 37.9
  },
  {
    "<TICKER>": "TWTR US",
    "<PER>": "D",
    "<DATE>": "7/24/19",
    "<TIME>": "00:00",
    "<CLOSE>": 38.73
  },
  {
    "<TICKER>": "TWTR US",
    "<PER>": "D",
    "<DATE>": "7/25/19",
    "<TIME>": "00:00",
    "<CLOSE>": 38.12
  },
  {
    "<TICKER>": "TWTR US",
    "<PER>": "D",
    "<DATE>": "7/26/19",
    "<TIME>": "00:00",
    "<CLOSE>": 41.52
  },
  {
    "<TICKER>": "TWTR US",
    "<PER>": "D",
    "<DATE>": "7/27/19",
    "<TIME>": "00:00",
    "<CLOSE>": 41.52
  },
  {
    "<TICKER>": "TWTR US",
    "<PER>": "D",
    "<DATE>": "7/28/19",
    "<TIME>": "00:00",
    "<CLOSE>": 41.52
  },
  {
    "<TICKER>": "TWTR US",
    "<PER>": "D",
    "<DATE>": "7/29/19",
    "<TIME>": "00:00",
    "<CLOSE>": 41.5
  },
  {
    "<TICKER>": "TWTR US",
    "<PER>": "D",
    "<DATE>": "7/30/19",
    "<TIME>": "00:00",
    "<CLOSE>": 41
  },
  {
    "<TICKER>": "TWTR US",
    "<PER>": "D",
    "<DATE>": "7/31/19",
    "<TIME>": "00:00",
    "<CLOSE>": 42.31
  },
  {
    "<TICKER>": "TWTR US",
    "<PER>": "D",
    "<DATE>": "8/1/19",
    "<TIME>": "00:00",
    "<CLOSE>": 42.08
  },
  {
    "<TICKER>": "TWTR US",
    "<PER>": "D",
    "<DATE>": "8/2/19",
    "<TIME>": "00:00",
    "<CLOSE>": 42.85
  },
  {
    "<TICKER>": "TWTR US",
    "<PER>": "D",
    "<DATE>": "8/3/19",
    "<TIME>": "00:00",
    "<CLOSE>": 42.85
  },
  {
    "<TICKER>": "TWTR US",
    "<PER>": "D",
    "<DATE>": "8/4/19",
    "<TIME>": "00:00",
    "<CLOSE>": 42.85
  },
  {
    "<TICKER>": "TWTR US",
    "<PER>": "D",
    "<DATE>": "8/5/19",
    "<TIME>": "00:00",
    "<CLOSE>": 40.37
  },
  {
    "<TICKER>": "TWTR US",
    "<PER>": "D",
    "<DATE>": "8/6/19",
    "<TIME>": "00:00",
    "<CLOSE>": 41.32
  },
  {
    "<TICKER>": "TWTR US",
    "<PER>": "D",
    "<DATE>": "8/7/19",
    "<TIME>": "00:00",
    "<CLOSE>": 41.73
  },
  {
    "<TICKER>": "TWTR US",
    "<PER>": "D",
    "<DATE>": "8/8/19",
    "<TIME>": "00:00",
    "<CLOSE>": 42.07
  },
  {
    "<TICKER>": "TWTR US",
    "<PER>": "D",
    "<DATE>": "8/9/19",
    "<TIME>": "00:00",
    "<CLOSE>": 41.53
  },
  {
    "<TICKER>": "TWTR US",
    "<PER>": "D",
    "<DATE>": "8/10/19",
    "<TIME>": "00:00",
    "<CLOSE>": 41.53
  },
  {
    "<TICKER>": "TWTR US",
    "<PER>": "D",
    "<DATE>": "8/11/19",
    "<TIME>": "00:00",
    "<CLOSE>": 41.53
  },
  {
    "<TICKER>": "TWTR US",
    "<PER>": "D",
    "<DATE>": "8/12/19",
    "<TIME>": "00:00",
    "<CLOSE>": 40.48
  },
  {
    "<TICKER>": "TWTR US",
    "<PER>": "D",
    "<DATE>": "8/13/19",
    "<TIME>": "00:00",
    "<CLOSE>": 41.81
  },
  {
    "<TICKER>": "TWTR US",
    "<PER>": "D",
    "<DATE>": "8/14/19",
    "<TIME>": "00:00",
    "<CLOSE>": 40.65
  },
  {
    "<TICKER>": "TWTR US",
    "<PER>": "D",
    "<DATE>": "8/15/19",
    "<TIME>": "00:00",
    "<CLOSE>": 40.09
  },
  {
    "<TICKER>": "TWTR US",
    "<PER>": "D",
    "<DATE>": "8/16/19",
    "<TIME>": "00:00",
    "<CLOSE>": 40.58
  },
  {
    "<TICKER>": "TWTR US",
    "<PER>": "D",
    "<DATE>": "8/17/19",
    "<TIME>": "00:00",
    "<CLOSE>": 40.58
  },
  {
    "<TICKER>": "TWTR US",
    "<PER>": "D",
    "<DATE>": "8/18/19",
    "<TIME>": "00:00",
    "<CLOSE>": 40.58
  },
  {
    "<TICKER>": "TWTR US",
    "<PER>": "D",
    "<DATE>": "8/19/19",
    "<TIME>": "00:00",
    "<CLOSE>": 41.7
  },
  {
    "<TICKER>": "TWTR US",
    "<PER>": "D",
    "<DATE>": "8/20/19",
    "<TIME>": "00:00",
    "<CLOSE>": 42.29
  },
  {
    "<TICKER>": "TWTR US",
    "<PER>": "D",
    "<DATE>": "8/21/19",
    "<TIME>": "00:00",
    "<CLOSE>": 42.8
  },
  {
    "<TICKER>": "TWTR US",
    "<PER>": "D",
    "<DATE>": "8/22/19",
    "<TIME>": "00:00",
    "<CLOSE>": 42.18
  },
  {
    "<TICKER>": "TWTR US",
    "<PER>": "D",
    "<DATE>": "8/23/19",
    "<TIME>": "00:00",
    "<CLOSE>": 41
  },
  {
    "<TICKER>": "TWTR US",
    "<PER>": "D",
    "<DATE>": "8/24/19",
    "<TIME>": "00:00",
    "<CLOSE>": 41
  },
  {
    "<TICKER>": "TWTR US",
    "<PER>": "D",
    "<DATE>": "8/25/19",
    "<TIME>": "00:00",
    "<CLOSE>": 41
  },
  {
    "<TICKER>": "TWTR US",
    "<PER>": "D",
    "<DATE>": "8/26/19",
    "<TIME>": "00:00",
    "<CLOSE>": 41.44
  },
  {
    "<TICKER>": "TWTR US",
    "<PER>": "D",
    "<DATE>": "8/27/19",
    "<TIME>": "00:00",
    "<CLOSE>": 42.14
  },
  {
    "<TICKER>": "TWTR US",
    "<PER>": "D",
    "<DATE>": "8/28/19",
    "<TIME>": "00:00",
    "<CLOSE>": 41.68
  },
  {
    "<TICKER>": "TWTR US",
    "<PER>": "D",
    "<DATE>": "8/29/19",
    "<TIME>": "00:00",
    "<CLOSE>": 42.49
  },
  {
    "<TICKER>": "TWTR US",
    "<PER>": "D",
    "<DATE>": "8/30/19",
    "<TIME>": "00:00",
    "<CLOSE>": 42.65
  },
  {
    "<TICKER>": "TWTR US",
    "<PER>": "D",
    "<DATE>": "8/31/19",
    "<TIME>": "00:00",
    "<CLOSE>": 42.65
  },
  {
    "<TICKER>": "TWTR US",
    "<PER>": "D",
    "<DATE>": "9/1/19",
    "<TIME>": "00:00",
    "<CLOSE>": 42.65
  },
  {
    "<TICKER>": "TWTR US",
    "<PER>": "D",
    "<DATE>": "9/2/19",
    "<TIME>": "00:00",
    "<CLOSE>": 42.65
  },
  {
    "<TICKER>": "TWTR US",
    "<PER>": "D",
    "<DATE>": "9/3/19",
    "<TIME>": "00:00",
    "<CLOSE>": 41.96
  },
  {
    "<TICKER>": "TWTR US",
    "<PER>": "D",
    "<DATE>": "9/4/19",
    "<TIME>": "00:00",
    "<CLOSE>": 43.36
  },
  {
    "<TICKER>": "TWTR US",
    "<PER>": "D",
    "<DATE>": "9/5/19",
    "<TIME>": "00:00",
    "<CLOSE>": 45.3
  },
  {
    "<TICKER>": "TWTR US",
    "<PER>": "D",
    "<DATE>": "9/6/19",
    "<TIME>": "00:00",
    "<CLOSE>": 45.42
  },
  {
    "<TICKER>": "TWTR US",
    "<PER>": "D",
    "<DATE>": "9/7/19",
    "<TIME>": "00:00",
    "<CLOSE>": 45.42
  },
  {
    "<TICKER>": "TWTR US",
    "<PER>": "D",
    "<DATE>": "9/8/19",
    "<TIME>": "00:00",
    "<CLOSE>": 45.42
  },
  {
    "<TICKER>": "TWTR US",
    "<PER>": "D",
    "<DATE>": "9/9/19",
    "<TIME>": "00:00",
    "<CLOSE>": 44.26
  },
  {
    "<TICKER>": "TWTR US",
    "<PER>": "D",
    "<DATE>": "9/10/19",
    "<TIME>": "00:00",
    "<CLOSE>": 43.25
  },
  {
    "<TICKER>": "TWTR US",
    "<PER>": "D",
    "<DATE>": "9/11/19",
    "<TIME>": "00:00",
    "<CLOSE>": 43.25
  },
  {
    "<TICKER>": "TWTR US",
    "<PER>": "D",
    "<DATE>": "9/12/19",
    "<TIME>": "00:00",
    "<CLOSE>": 43.2
  },
  {
    "<TICKER>": "TWTR US",
    "<PER>": "D",
    "<DATE>": "9/13/19",
    "<TIME>": "00:00",
    "<CLOSE>": 42.63
  },
  {
    "<TICKER>": "TWTR US",
    "<PER>": "D",
    "<DATE>": "9/14/19",
    "<TIME>": "00:00",
    "<CLOSE>": 42.63
  },
  {
    "<TICKER>": "TWTR US",
    "<PER>": "D",
    "<DATE>": "9/15/19",
    "<TIME>": "00:00",
    "<CLOSE>": 42.63
  },
  {
    "<TICKER>": "TWTR US",
    "<PER>": "D",
    "<DATE>": "9/16/19",
    "<TIME>": "00:00",
    "<CLOSE>": 42.76
  },
  {
    "<TICKER>": "TWTR US",
    "<PER>": "D",
    "<DATE>": "9/17/19",
    "<TIME>": "00:00",
    "<CLOSE>": 43.24
  },
  {
    "<TICKER>": "TWTR US",
    "<PER>": "D",
    "<DATE>": "9/18/19",
    "<TIME>": "00:00",
    "<CLOSE>": 43.24
  },
  {
    "<TICKER>": "TWTR US",
    "<PER>": "D",
    "<DATE>": "9/19/19",
    "<TIME>": "00:00",
    "<CLOSE>": 42.93
  },
  {
    "<TICKER>": "TWTR US",
    "<PER>": "D",
    "<DATE>": "9/20/19",
    "<TIME>": "00:00",
    "<CLOSE>": 43.23
  },
  {
    "<TICKER>": "TWTR US",
    "<PER>": "D",
    "<DATE>": "9/21/19",
    "<TIME>": "00:00",
    "<CLOSE>": 43.23
  },
  {
    "<TICKER>": "TWTR US",
    "<PER>": "D",
    "<DATE>": "9/22/19",
    "<TIME>": "00:00",
    "<CLOSE>": 43.23
  },
  {
    "<TICKER>": "TWTR US",
    "<PER>": "D",
    "<DATE>": "9/23/19",
    "<TIME>": "00:00",
    "<CLOSE>": 43.38
  },
  {
    "<TICKER>": "TWTR US",
    "<PER>": "D",
    "<DATE>": "9/24/19",
    "<TIME>": "00:00",
    "<CLOSE>": 41.42
  },
  {
    "<TICKER>": "TWTR US",
    "<PER>": "D",
    "<DATE>": "9/25/19",
    "<TIME>": "00:00",
    "<CLOSE>": 42.5
  },
  {
    "<TICKER>": "TWTR US",
    "<PER>": "D",
    "<DATE>": "9/26/19",
    "<TIME>": "00:00",
    "<CLOSE>": 42.44
  },
  {
    "<TICKER>": "TWTR US",
    "<PER>": "D",
    "<DATE>": "9/27/19",
    "<TIME>": "00:00",
    "<CLOSE>": 41.35
  },
  {
    "<TICKER>": "TWTR US",
    "<PER>": "D",
    "<DATE>": "9/28/19",
    "<TIME>": "00:00",
    "<CLOSE>": 41.35
  },
  {
    "<TICKER>": "TWTR US",
    "<PER>": "D",
    "<DATE>": "9/29/19",
    "<TIME>": "00:00",
    "<CLOSE>": 41.35
  },
  {
    "<TICKER>": "TWTR US",
    "<PER>": "D",
    "<DATE>": "9/30/19",
    "<TIME>": "00:00",
    "<CLOSE>": 41.2
  },
  {
    "<TICKER>": "TWTR US",
    "<PER>": "D",
    "<DATE>": "10/1/19",
    "<TIME>": "00:00",
    "<CLOSE>": 40.25
  },
  {
    "<TICKER>": "TWTR US",
    "<PER>": "D",
    "<DATE>": "10/2/19",
    "<TIME>": "00:00",
    "<CLOSE>": 39.7
  },
  {
    "<TICKER>": "TWTR US",
    "<PER>": "D",
    "<DATE>": "10/3/19",
    "<TIME>": "00:00",
    "<CLOSE>": 40
  },
  {
    "<TICKER>": "TWTR US",
    "<PER>": "D",
    "<DATE>": "10/4/19",
    "<TIME>": "00:00",
    "<CLOSE>": 40.36
  },
  {
    "<TICKER>": "TWTR US",
    "<PER>": "D",
    "<DATE>": "10/5/19",
    "<TIME>": "00:00",
    "<CLOSE>": 40.36
  },
  {
    "<TICKER>": "TWTR US",
    "<PER>": "D",
    "<DATE>": "10/6/19",
    "<TIME>": "00:00",
    "<CLOSE>": 40.36
  },
  {
    "<TICKER>": "TWTR US",
    "<PER>": "D",
    "<DATE>": "10/7/19",
    "<TIME>": "00:00",
    "<CLOSE>": 40.8
  },
  {
    "<TICKER>": "TWTR US",
    "<PER>": "D",
    "<DATE>": "10/8/19",
    "<TIME>": "00:00",
    "<CLOSE>": 39.7
  },
  {
    "<TICKER>": "TWTR US",
    "<PER>": "D",
    "<DATE>": "10/9/19",
    "<TIME>": "00:00",
    "<CLOSE>": 39.5
  },
  {
    "<TICKER>": "TWTR US",
    "<PER>": "D",
    "<DATE>": "10/10/19",
    "<TIME>": "00:00",
    "<CLOSE>": 39.54
  },
  {
    "<TICKER>": "TWTR US",
    "<PER>": "D",
    "<DATE>": "10/11/19",
    "<TIME>": "00:00",
    "<CLOSE>": 40.36
  },
  {
    "<TICKER>": "TWTR US",
    "<PER>": "D",
    "<DATE>": "10/12/19",
    "<TIME>": "00:00",
    "<CLOSE>": 40.36
  },
  {
    "<TICKER>": "TWTR US",
    "<PER>": "D",
    "<DATE>": "10/13/19",
    "<TIME>": "00:00",
    "<CLOSE>": 40.36
  },
  {
    "<TICKER>": "TWTR US",
    "<PER>": "D",
    "<DATE>": "10/14/19",
    "<TIME>": "00:00",
    "<CLOSE>": 39.78
  },
  {
    "<TICKER>": "TWTR US",
    "<PER>": "D",
    "<DATE>": "10/15/19",
    "<TIME>": "00:00",
    "<CLOSE>": 40.28
  },
  {
    "<TICKER>": "TWTR US",
    "<PER>": "D",
    "<DATE>": "10/16/19",
    "<TIME>": "00:00",
    "<CLOSE>": 39.91
  },
  {
    "<TICKER>": "TWTR US",
    "<PER>": "D",
    "<DATE>": "10/17/19",
    "<TIME>": "00:00",
    "<CLOSE>": 39.61
  },
  {
    "<TICKER>": "TWTR US",
    "<PER>": "D",
    "<DATE>": "10/18/19",
    "<TIME>": "00:00",
    "<CLOSE>": 38.99
  },
  {
    "<TICKER>": "TWTR US",
    "<PER>": "D",
    "<DATE>": "10/19/19",
    "<TIME>": "00:00",
    "<CLOSE>": 38.99
  },
  {
    "<TICKER>": "TWTR US",
    "<PER>": "D",
    "<DATE>": "10/20/19",
    "<TIME>": "00:00",
    "<CLOSE>": 38.99
  },
  {
    "<TICKER>": "TWTR US",
    "<PER>": "D",
    "<DATE>": "10/21/19",
    "<TIME>": "00:00",
    "<CLOSE>": 40.09
  },
  {
    "<TICKER>": "TWTR US",
    "<PER>": "D",
    "<DATE>": "10/22/19",
    "<TIME>": "00:00",
    "<CLOSE>": 38.81
  },
  {
    "<TICKER>": "TWTR US",
    "<PER>": "D",
    "<DATE>": "10/23/19",
    "<TIME>": "00:00",
    "<CLOSE>": 38.83
  },
  {
    "<TICKER>": "TWTR US",
    "<PER>": "D",
    "<DATE>": "10/24/19",
    "<TIME>": "00:00",
    "<CLOSE>": 30.75
  },
  {
    "<TICKER>": "TWTR US",
    "<PER>": "D",
    "<DATE>": "10/25/19",
    "<TIME>": "00:00",
    "<CLOSE>": 30.3
  },
  {
    "<TICKER>": "TWTR US",
    "<PER>": "D",
    "<DATE>": "10/26/19",
    "<TIME>": "00:00",
    "<CLOSE>": 30.3
  },
  {
    "<TICKER>": "TWTR US",
    "<PER>": "D",
    "<DATE>": "10/27/19",
    "<TIME>": "00:00",
    "<CLOSE>": 30.3
  },
  {
    "<TICKER>": "TWTR US",
    "<PER>": "D",
    "<DATE>": "10/28/19",
    "<TIME>": "00:00",
    "<CLOSE>": 30.06
  },
  {
    "<TICKER>": "TWTR US",
    "<PER>": "D",
    "<DATE>": "10/29/19",
    "<TIME>": "00:00",
    "<CLOSE>": 29.85
  },
  {
    "<TICKER>": "TWTR US",
    "<PER>": "D",
    "<DATE>": "10/30/19",
    "<TIME>": "00:00",
    "<CLOSE>": 29.86
  },
  {
    "<TICKER>": "TWTR US",
    "<PER>": "D",
    "<DATE>": "10/31/19",
    "<TIME>": "00:00",
    "<CLOSE>": 29.97
  },
  {
    "<TICKER>": "TWTR US",
    "<PER>": "D",
    "<DATE>": "11/1/19",
    "<TIME>": "00:00",
    "<CLOSE>": 29.62
  },
  {
    "<TICKER>": "TWTR US",
    "<PER>": "D",
    "<DATE>": "11/2/19",
    "<TIME>": "00:00",
    "<CLOSE>": 29.62
  },
  {
    "<TICKER>": "TWTR US",
    "<PER>": "D",
    "<DATE>": "11/3/19",
    "<TIME>": "00:00",
    "<CLOSE>": 29.62
  },
  {
    "<TICKER>": "TWTR US",
    "<PER>": "D",
    "<DATE>": "11/4/19",
    "<TIME>": "00:00",
    "<CLOSE>": 30.05
  },
  {
    "<TICKER>": "TWTR US",
    "<PER>": "D",
    "<DATE>": "11/5/19",
    "<TIME>": "00:00",
    "<CLOSE>": 29.81
  },
  {
    "<TICKER>": "TWTR US",
    "<PER>": "D",
    "<DATE>": "11/6/19",
    "<TIME>": "00:00",
    "<CLOSE>": 29.54
  },
  {
    "<TICKER>": "TWTR US",
    "<PER>": "D",
    "<DATE>": "11/7/19",
    "<TIME>": "00:00",
    "<CLOSE>": 29.05
  },
  {
    "<TICKER>": "TWTR US",
    "<PER>": "D",
    "<DATE>": "11/8/19",
    "<TIME>": "00:00",
    "<CLOSE>": 29.21
  },
  {
    "<TICKER>": "TWTR US",
    "<PER>": "D",
    "<DATE>": "11/9/19",
    "<TIME>": "00:00",
    "<CLOSE>": 29.21
  },
  {
    "<TICKER>": "TWTR US",
    "<PER>": "D",
    "<DATE>": "11/10/19",
    "<TIME>": "00:00",
    "<CLOSE>": 29.21
  },
  {
    "<TICKER>": "TWTR US",
    "<PER>": "D",
    "<DATE>": "11/11/19",
    "<TIME>": "00:00",
    "<CLOSE>": 29.34
  },
  {
    "<TICKER>": "TWTR US",
    "<PER>": "D",
    "<DATE>": "11/12/19",
    "<TIME>": "00:00",
    "<CLOSE>": 29.05
  },
  {
    "<TICKER>": "TWTR US",
    "<PER>": "D",
    "<DATE>": "11/13/19",
    "<TIME>": "00:00",
    "<CLOSE>": 29.08
  },
  {
    "<TICKER>": "TWTR US",
    "<PER>": "D",
    "<DATE>": "11/14/19",
    "<TIME>": "00:00",
    "<CLOSE>": 28.89
  },
  {
    "<TICKER>": "TWTR US",
    "<PER>": "D",
    "<DATE>": "11/15/19",
    "<TIME>": "00:00",
    "<CLOSE>": 29.25
  },
  {
    "<TICKER>": "TWTR US",
    "<PER>": "D",
    "<DATE>": "11/16/19",
    "<TIME>": "00:00",
    "<CLOSE>": 29.25
  },
  {
    "<TICKER>": "TWTR US",
    "<PER>": "D",
    "<DATE>": "11/17/19",
    "<TIME>": "00:00",
    "<CLOSE>": 29.25
  },
  {
    "<TICKER>": "TWTR US",
    "<PER>": "D",
    "<DATE>": "11/18/19",
    "<TIME>": "00:00",
    "<CLOSE>": 29.49
  },
  {
    "<TICKER>": "TWTR US",
    "<PER>": "D",
    "<DATE>": "11/19/19",
    "<TIME>": "00:00",
    "<CLOSE>": 29.44
  },
  {
    "<TICKER>": "TWTR US",
    "<PER>": "D",
    "<DATE>": "11/20/19",
    "<TIME>": "00:00",
    "<CLOSE>": 29.17
  },
  {
    "<TICKER>": "TWTR US",
    "<PER>": "D",
    "<DATE>": "11/21/19",
    "<TIME>": "00:00",
    "<CLOSE>": 29.79
  },
  {
    "<TICKER>": "TWTR US",
    "<PER>": "D",
    "<DATE>": "11/22/19",
    "<TIME>": "00:00",
    "<CLOSE>": 30.03
  },
  {
    "<TICKER>": "TWTR US",
    "<PER>": "D",
    "<DATE>": "11/23/19",
    "<TIME>": "00:00",
    "<CLOSE>": 30.03
  },
  {
    "<TICKER>": "TWTR US",
    "<PER>": "D",
    "<DATE>": "11/24/19",
    "<TIME>": "00:00",
    "<CLOSE>": 30.03
  },
  {
    "<TICKER>": "TWTR US",
    "<PER>": "D",
    "<DATE>": "11/25/19",
    "<TIME>": "00:00",
    "<CLOSE>": 30.54
  },
  {
    "<TICKER>": "TWTR US",
    "<PER>": "D",
    "<DATE>": "11/26/19",
    "<TIME>": "00:00",
    "<CLOSE>": 30.96
  },
  {
    "<TICKER>": "TWTR US",
    "<PER>": "D",
    "<DATE>": "11/27/19",
    "<TIME>": "00:00",
    "<CLOSE>": 31.17
  },
  {
    "<TICKER>": "TWTR US",
    "<PER>": "D",
    "<DATE>": "11/28/19",
    "<TIME>": "00:00",
    "<CLOSE>": 31.17
  },
  {
    "<TICKER>": "TWTR US",
    "<PER>": "D",
    "<DATE>": "11/29/19",
    "<TIME>": "00:00",
    "<CLOSE>": 30.91
  },
  {
    "<TICKER>": "TWTR US",
    "<PER>": "D",
    "<DATE>": "11/30/19",
    "<TIME>": "00:00",
    "<CLOSE>": 30.91
  },
  {
    "<TICKER>": "TWTR US",
    "<PER>": "D",
    "<DATE>": "12/1/19",
    "<TIME>": "00:00",
    "<CLOSE>": 30.91
  },
  {
    "<TICKER>": "TWTR US",
    "<PER>": "D",
    "<DATE>": "12/2/19",
    "<TIME>": "00:00",
    "<CLOSE>": 30.42
  },
  {
    "<TICKER>": "TWTR US",
    "<PER>": "D",
    "<DATE>": "12/3/19",
    "<TIME>": "00:00",
    "<CLOSE>": 29.97
  },
  {
    "<TICKER>": "TWTR US",
    "<PER>": "D",
    "<DATE>": "12/4/19",
    "<TIME>": "00:00",
    "<CLOSE>": 30
  },
  {
    "<TICKER>": "TWTR US",
    "<PER>": "D",
    "<DATE>": "12/5/19",
    "<TIME>": "00:00",
    "<CLOSE>": 30.04
  },
  {
    "<TICKER>": "TWTR US",
    "<PER>": "D",
    "<DATE>": "12/6/19",
    "<TIME>": "00:00",
    "<CLOSE>": 30.19
  },
  {
    "<TICKER>": "TWTR US",
    "<PER>": "D",
    "<DATE>": "12/7/19",
    "<TIME>": "00:00",
    "<CLOSE>": 30.19
  },
  {
    "<TICKER>": "TWTR US",
    "<PER>": "D",
    "<DATE>": "12/8/19",
    "<TIME>": "00:00",
    "<CLOSE>": 30.19
  },
  {
    "<TICKER>": "TWTR US",
    "<PER>": "D",
    "<DATE>": "12/9/19",
    "<TIME>": "00:00",
    "<CLOSE>": 30.21
  },
  {
    "<TICKER>": "TWTR US",
    "<PER>": "D",
    "<DATE>": "12/10/19",
    "<TIME>": "00:00",
    "<CLOSE>": 29.84
  },
  {
    "<TICKER>": "TWTR US",
    "<PER>": "D",
    "<DATE>": "12/11/19",
    "<TIME>": "00:00",
    "<CLOSE>": 30.55
  },
  {
    "<TICKER>": "TWTR US",
    "<PER>": "D",
    "<DATE>": "12/12/19",
    "<TIME>": "00:00",
    "<CLOSE>": 30.3
  },
  {
    "<TICKER>": "TWTR US",
    "<PER>": "D",
    "<DATE>": "12/13/19",
    "<TIME>": "00:00",
    "<CLOSE>": 30.39
  },
  {
    "<TICKER>": "TWTR US",
    "<PER>": "D",
    "<DATE>": "12/14/19",
    "<TIME>": "00:00",
    "<CLOSE>": 30.39
  },
  {
    "<TICKER>": "TWTR US",
    "<PER>": "D",
    "<DATE>": "12/15/19",
    "<TIME>": "00:00",
    "<CLOSE>": 30.39
  },
  {
    "<TICKER>": "TWTR US",
    "<PER>": "D",
    "<DATE>": "12/16/19",
    "<TIME>": "00:00",
    "<CLOSE>": 30.97
  },
  {
    "<TICKER>": "TWTR US",
    "<PER>": "D",
    "<DATE>": "12/17/19",
    "<TIME>": "00:00",
    "<CLOSE>": 30.7
  },
  {
    "<TICKER>": "TWTR US",
    "<PER>": "D",
    "<DATE>": "12/18/19",
    "<TIME>": "00:00",
    "<CLOSE>": 31.68
  },
  {
    "<TICKER>": "TWTR US",
    "<PER>": "D",
    "<DATE>": "12/19/19",
    "<TIME>": "00:00",
    "<CLOSE>": 32.03
  },
  {
    "<TICKER>": "TWTR US",
    "<PER>": "D",
    "<DATE>": "12/20/19",
    "<TIME>": "00:00",
    "<CLOSE>": 32.13
  },
  {
    "<TICKER>": "TWTR US",
    "<PER>": "D",
    "<DATE>": "12/21/19",
    "<TIME>": "00:00",
    "<CLOSE>": 32.13
  },
  {
    "<TICKER>": "TWTR US",
    "<PER>": "D",
    "<DATE>": "12/22/19",
    "<TIME>": "00:00",
    "<CLOSE>": 32.13
  },
  {
    "<TICKER>": "TWTR US",
    "<PER>": "D",
    "<DATE>": "12/23/19",
    "<TIME>": "00:00",
    "<CLOSE>": 32.43
  },
  {
    "<TICKER>": "TWTR US",
    "<PER>": "D",
    "<DATE>": "12/24/19",
    "<TIME>": "00:00",
    "<CLOSE>": 32.5
  },
  {
    "<TICKER>": "TWTR US",
    "<PER>": "D",
    "<DATE>": "12/25/19",
    "<TIME>": "00:00",
    "<CLOSE>": 32.5
  },
  {
    "<TICKER>": "TWTR US",
    "<PER>": "D",
    "<DATE>": "12/26/19",
    "<TIME>": "00:00",
    "<CLOSE>": 32.63
  },
  {
    "<TICKER>": "TWTR US",
    "<PER>": "D",
    "<DATE>": "12/27/19",
    "<TIME>": "00:00",
    "<CLOSE>": 32.55
  },
  {
    "<TICKER>": "TWTR US",
    "<PER>": "D",
    "<DATE>": "12/28/19",
    "<TIME>": "00:00",
    "<CLOSE>": 32.55
  },
  {
    "<TICKER>": "TWTR US",
    "<PER>": "D",
    "<DATE>": "12/29/19",
    "<TIME>": "00:00",
    "<CLOSE>": 32.55
  },
  {
    "<TICKER>": "TWTR US",
    "<PER>": "D",
    "<DATE>": "12/30/19",
    "<TIME>": "00:00",
    "<CLOSE>": 32.03
  },
  {
    "<TICKER>": "TWTR US",
    "<PER>": "D",
    "<DATE>": "12/31/19",
    "<TIME>": "00:00",
    "<CLOSE>": 32.05
  }
]